data_mem.v
module data_mem(
    input clk,
    input logic mem_read,
    input logic mem_write,
    input logic [31:0] addr,
    input logic [31:0] data_in,

    output logic [31:0] data_out
);

    logic [31:0] mem [255:0];

    // always_comb begin
    //     if(mem_read)
    //         data_out = mem[addr[9:2]];
    //     else
    //         data_out = 32'd0;
    // end

    assign data_out = (mem_read) ? mem[addr[9:2]] : 32'd0;

    // RAM doesn't need to be reset
    // here both data and instruction memory is byte indexed
    // byte index means every byte have address

    always_ff @(posedge clk) begin

        if (mem_write) begin
            mem[addr[9:2]] <= data_in;
        end
        
    end

    
endmodule

rtl/core/alu.v
module alu(
    input wire [31:0] a,
    input wire [31:0] b,
    input wire [3:0] alu_ctrl,
    output reg [31:0] result,
    output wire zero 
);

localparam ADD = 4'b0000;
localparam SUB = 4'b0001;
localparam AND = 4'b0010;
localparam OR  = 4'b0011;
localparam XOR = 4'b0100;
localparam SLL = 4'b0101;
localparam SRL = 4'b0110;
localparam SRA = 4'b0111;
localparam SLT = 4'b1000;
localparam SLTU = 4'b1001;

// Combinational logic: use blocking assignment (=) not non-blocking (<=)
// Blocking assignment ensures immediate evaluation (critical for combinational)
// Non-blocking (<=) would give stale values in combinational blocks

    always @(*) begin
        case (alu_ctrl)
            ADD: result = a + b;
            SUB: result = a - b;
            AND: result = a & b;
            OR: result = a | b; 
            XOR: result = a ^ b;
            // RV32 register and immediate shifts use only the low five bits.
            SLL: result = a << b[4:0];
            SRL: result = a >> b[4:0];
            SRA: result = $signed(a) >>> b[4:0];
            SLT: result = ($signed(a)<$signed(b)) ? 32'd1 : 32'd0;
            SLTU: result = (a<b) ? 32'd1 : 32'd0;
            default: result = 32'd0;
        endcase
    end

    assign zero = (result == 32'd0);
    
endmodule

rtl/imm_gen.v
module imm_gen(
    input wire [31:0] instr,
    output reg [31:0] imm
);
    wire [6:0] opcode = instr[6:0];

    localparam I_TYPE = 7'b0010011;
    localparam LOAD   = 7'b0000011;
    localparam STORE  = 7'b0100011;
    localparam BRANCH = 7'b1100011;

    always @(*) begin
        case (opcode)
            I_TYPE,
            LOAD:
                imm = {{20{instr[31]}}, instr[31:20]};

            STORE:
                imm = {{20{instr[31]}}, instr[31:25], instr[11:7]};

            BRANCH:
                imm = {{19{instr[31]}}, instr[31], instr[7],
                       instr[30:25], instr[11:8], 1'b0};

            default:
                imm = 32'd0;
        endcase
    end
endmodule

register_file.v
module register_file(
    input logic clk,
    input logic we,
    input logic [4:0] rs1,
    input logic [4:0] rs2,
    input logic [4:0] rd,
    input logic [31:0] wd,
    output logic [31:0] rd1,
    output logic [31:0] rd2
);

    logic [31:0] regfile [31:0];

    //for immidiate access of register file we used combinational/dataflow modelling.
    assign rd1 = regfile[rs1];
    assign rd2 = regfile[rs2];

    // since in write value is changing and output depends on state and input hence sequential unlike read.
    always_ff @(posedge clk) begin
        if(we && rd != 0)
            regfile[rd] <= wd;
    end

endmodule

rtl/control_unit.v
module control_unit(
    input wire [6:0] opcode,
    input wire [2:0] func3,
    input wire [6:0] func7,

    output reg reg_write,
    output reg mem_read,
    output reg mem_write,
    output reg alu_src,
    output reg branch,
    output reg [3:0] alu_ctrl
);
    localparam R_TYPE = 7'b0110011;    // Register-Register
    localparam I_TYPE = 7'b0010011;    // Immediate
    localparam LOAD   = 7'b0000011;    // Load
    localparam STORE  = 7'b0100011;    // Store
    localparam BRANCH = 7'b1100011;    // Branch

    always @(*) begin
        // Default: prevent latches
        reg_write = 0;
        mem_read = 0;
        mem_write = 0;
        alu_src = 0;
        branch = 0;
        alu_ctrl = 4'b0000;

        case (opcode)
            R_TYPE: begin
                reg_write = 1;
                case({func7, func3})
                    {7'b0000000, 3'b000}: alu_ctrl = 4'b0000;  // ADD
                    {7'b0100000, 3'b000}: alu_ctrl = 4'b0001;  // SUB
                    {7'b0000000, 3'b111}: alu_ctrl = 4'b0010;  // AND
                    {7'b0000000, 3'b110}: alu_ctrl = 4'b0011;  // OR
                    {7'b0000000, 3'b001}: alu_ctrl = 4'b0101;  // SLL
                    {7'b0000000, 3'b010}: alu_ctrl = 4'b1000;  // SLT
                    {7'b0000000, 3'b011}: alu_ctrl = 4'b1001;  // SLTU
                    {7'b0000000, 3'b100}: alu_ctrl = 4'b0100;  // XOR
                    {7'b0000000, 3'b101}: alu_ctrl = 4'b0110;  // SRL
                    {7'b0100000, 3'b101}: alu_ctrl = 4'b0111;  // SRA
                    default: alu_ctrl = 4'b1111;
                endcase
            end
            I_TYPE: begin
                reg_write = 1;
                alu_src = 1;
                case (func3)
                    3'b000: alu_ctrl = 4'b0000;  // ADDI
                    3'b010: alu_ctrl = 4'b1000;  // SLTI
                    3'b011: alu_ctrl = 4'b1001;  // SLTU
                    3'b100: alu_ctrl = 4'b0100;  // XORI
                    3'b110: alu_ctrl = 4'b0011;  // ORI
                    3'b111: alu_ctrl = 4'b0010;  // ANDI
                    end
                endcase
            end
            LOAD: begin
                case (func3)
                    3'b010: begin // LW
                        reg_write = 1;
                        mem_read = 1;
                        alu_src = 1;
                        alu_ctrl = 4'b0000;
                    end
                endcase
            end
            STORE: begin
                case (func3)
                    3'b010: begin // SW
                        mem_write = 1;
                        alu_src = 1;
                        alu_ctrl = 4'b0000;
                    end
                endcase
            end
            BRANCH: begin
                case (func3)
                    3'b000: begin // BEQ
                        branch = 1;
                        alu_ctrl = 4'b0001;
                    end
                endcase
            end
        endcase
    end

endmodule

rtl/mem.v
module inst_mem(
    input wire clk,
    input wire [31:0] addr,
    output wire [31:0] instruction
    // Add programing Interface
    input wire [31:0] prog_addr,
    input wire [31:0] prog_data,
    input wire        prog_we
);
    reg [31:0] mem [255:0];

    always @(posedge clk) begin
        if(prog_we)
            mem[prog_addr] <= prog_data;
    end
    // addr[9:2] converts byte address to word index
    assign instruction = mem[addr[9:2]];

endmodule

rtl/pc_rtl.v
module pc (
    input logic clk,
    input logic rst,
    input logic [31:0] next_pc,
    output logic [31:0] pc
);
    always @(posedge clk or posedge rst) begin
        if(rst)
            pc <= 0;
        else
            pc <= next_pc;
    end

endmodule

rtl/riscv_core.v
module riscv_core(
    input wire clk,
    input wire reset,
    // Add programing Interface
    input wire [31:0] prog_addr,
    input wire [31:0] prog_data,
    input wire        prog_we,

    output wire [31:0] dbg_pc,
    output wire [31:0] dbg_instr,
    output wire        dbg_reg_write,
    output wire [4:0]  dbg_rd,
    output wire [31:0] dbg_writeback_data,
    output wire        dbg_mem_write,
    output wire [31:0] dbg_mem_addr,
    output wire [31:0] dbg_mem_wdata,
    output wire        dbg_commit_valid
);

    //----------------------PC-----------------------
    wire [31:0] pc, next_pc;

    pc pc_inst (
        .clk(clk),
        .rst(reset),
        .next_pc(next_pc),
        .pc(pc)
    );

    //-------------------Instruction Memory----------
    wire [31:0] instr;
    inst_mem imem(
        .clk(clk),
        .addr(pc),
        .instruction(instr),
        .prog_addr(prog_addr),
        .prog_data(prog_data),
        .prog_we(prog_we)
    );

    //-----------------DECODE-----------------------
    wire [6:0] opcode;
    wire [2:0] func3;
    wire [6:0] func7;

    assign opcode = instr[6:0];
    assign func3 = instr[14:12];
    assign func7 = instr[31:25];

    //----------------Control Unit-----------------
    wire reg_write, mem_read, mem_write, alu_src, branch;
    wire [3:0] alu_ctrl;

    control_unit cu (
    .opcode(opcode),
    .func3(func3),
    .func7(func7),
    .reg_write(reg_write),
    .mem_read(mem_read),
    .mem_write(mem_write),
    .alu_src(alu_src),
    .branch(branch),
    .alu_ctrl(alu_ctrl)
);

// -------------------- Register File --------------------
wire [4:0] rs1, rs2, rd;
wire [31:0] rd1, rd2, write_data;

assign rs1 = instr[19:15];
assign rs2 = instr[24:20];
assign rd  = instr[11:7];

register_file rf (
    .clk(clk),
    .we(reg_write),
    .rs1(rs1),
    .rs2(rs2),
    .rd(rd),
    .wd(write_data),
    .rd1(rd1),
    .rd2(rd2)
);

// -------------------- Immediate Generator --------------------
wire [31:0] imm;

imm_gen imm_gen_inst (
    .instr(instr),
    .imm(imm)
);

// -------------------- ALU --------------------
wire [31:0] alu_in2, alu_result;
wire zero;

assign alu_in2 = (alu_src) ? imm : rd2;

alu alu_inst (
    .a(rd1),
    .b(alu_in2),
    .alu_ctrl(alu_ctrl),
    .result(alu_result),
    .zero(zero)
);

// -------------------- Data Memory --------------------
wire [31:0] data_out;

data_mem dmem (
    .clk(clk),
    .mem_read(mem_read),
    .mem_write(mem_write),
    .addr(alu_result),
    .data_in(rd2),
    .data_out(data_out)
);

// -------------------- Write Back --------------------
assign write_data = (mem_read) ? data_out : alu_result;      //for LOAD write_data = data_out and for add sub and other arthmatic operation write_data = alu_result

// -------------------- PC Update --------------------
assign next_pc = (branch && zero) ? pc + imm : pc + 4;       // branch is output of cu

// -------------------- Debug/Verification Interface --------------------
assign dbg_pc = pc;
assign dbg_instr = instr;
assign dbg_reg_write = reg_write;
assign dbg_rd = rd;
assign dbg_writeback_data = write_data;
assign dbg_mem_write = mem_write;
assign dbg_mem_addr = alu_result;
assign dbg_mem_wdata = rd2;
assign dbg_commit_valid = !reset && !prog_we;
    
endmodule

tb/tb_riscv_core.v
`timescale 1ns/1ps

module tb_riscv_core;
    
    // Testbench signals
    reg clk;
    reg reset;
    
    // Instantiate your RISC-V core
    riscv_core dut (
        .clk(clk),
        .reset(reset),
        .prog_addr(32'd0),
        .prog_data(32'd0),
        .prog_we(1'b0)
    );
    
    // Clock generation: 10ns period (100MHz)
    initial clk = 0;
    always #5 clk = ~clk;
    
    // Test program
    initial begin
        // Setup waveform dump
        $dumpfile("riscv.vcd");
        $dumpvars(0, tb_riscv_core);
        
        // Initialize instruction memory with program
        // Program:
        //   addi x1, x0, 5    -> x1 = 5
        //   addi x2, x0, 3    -> x2 = 3
        //   add  x3, x1, x2   -> x3 = 8
        //   sub  x4, x3, x2   -> x4 = 5
        //   sw   x3, 0(x0)    -> mem[0] = 8
        //   lw   x5, 0(x0)    -> x5 = 8
        //   beq  x5, x3, +8   -> skip next instruction
        //   addi x6, x0, 1    -> skipped
        //   addi x7, x0, 9    -> x7 = 9
        
        dut.imem.mem[0] = 32'h00500093;  // addi x1, x0, 5
        dut.imem.mem[1] = 32'h00300113;  // addi x2, x0, 3
        dut.imem.mem[2] = 32'h002081b3;  // add  x3, x1, x2
      	dut.imem.mem[3] = 32'h40218233;  // sub  x4, x3, x2
        dut.imem.mem[4] = 32'h00302023;  // sw   x3, 0(x0)
        dut.imem.mem[5] = 32'h00002283;  // lw   x5, 0(x0)
        dut.imem.mem[6] = 32'h00328463;  // beq  x5, x3, +8
        dut.imem.mem[7] = 32'h00100313;  // addi x6, x0, 1 (skipped)
        dut.imem.mem[8] = 32'h00900393;  // addi x7, x0, 9
        
        // Apply reset
        reset = 1;
        repeat (2) @(posedge clk);
        reset = 0;
        
        // Run for enough cycles
        repeat (14) @(posedge clk);
        
        // Display results
        $display("\n========== Test Results ==========");
        $display("x1 = %0d (expected: 5)", dut.rf.regfile[1]);
        $display("x2 = %0d (expected: 3)", dut.rf.regfile[2]);
        $display("x3 = %0d (expected: 8)", dut.rf.regfile[3]);
        $display("x4 = %0d (expected: 5)", dut.rf.regfile[4]);
        $display("x5 = %0d (expected: 8)", dut.rf.regfile[5]);
        $display("x7 = %0d (expected: 9)", dut.rf.regfile[7]);
        $display("mem[0] = %0d (expected: 8)", dut.dmem.mem[0]);
        $display("==================================\n");
        
        // Check if test passed
        if (dut.rf.regfile[1] == 5 &&
            dut.rf.regfile[2] == 3 &&
            dut.rf.regfile[3] == 8 &&
            dut.rf.regfile[4] == 5 &&
            dut.rf.regfile[5] == 8 &&
            dut.rf.regfile[7] == 9 &&
            dut.dmem.mem[0] == 8) begin
            $display("TEST PASSED!\n");
        end else begin
            $display("TEST FAILED!\n");
        end
        
        $finish;
    end
    
endmodule

riscv.vcd
$date
	Wed Jul  8 16:21:16 2026
$end
$version
	Icarus Verilog
$end
$timescale
	1ps
$end
$scope module tb_riscv_core $end
$var reg 1 ! clk $end
$var reg 1 " reset $end
$scope module dut $end
$var wire 1 ! clk $end
$var wire 1 # dbg_commit_valid $end
$var wire 32 $ dbg_instr [31:0] $end
$var wire 32 % dbg_mem_addr [31:0] $end
$var wire 32 & dbg_mem_wdata [31:0] $end
$var wire 1 ' dbg_mem_write $end
$var wire 32 ( dbg_pc [31:0] $end
$var wire 5 ) dbg_rd [4:0] $end
$var wire 1 * dbg_reg_write $end
$var wire 32 + dbg_writeback_data [31:0] $end
$var wire 32 , prog_addr [31:0] $end
$var wire 32 - prog_data [31:0] $end
$var wire 1 . prog_we $end
$var wire 1 " reset $end
$var wire 1 / zero $end
$var wire 32 0 write_data [31:0] $end
$var wire 5 1 rs2 [4:0] $end
$var wire 5 2 rs1 [4:0] $end
$var wire 1 3 reg_write $end
$var wire 32 4 rd2 [31:0] $end
$var wire 32 5 rd1 [31:0] $end
$var wire 5 6 rd [4:0] $end
$var wire 32 7 pc [31:0] $end
$var wire 7 8 opcode [6:0] $end
$var wire 32 9 next_pc [31:0] $end
$var wire 1 : mem_write $end
$var wire 1 ; mem_read $end
$var wire 32 < instr [31:0] $end
$var wire 32 = imm [31:0] $end
$var wire 7 > func7 [6:0] $end
$var wire 3 ? func3 [2:0] $end
$var wire 32 @ data_out [31:0] $end
$var wire 1 A branch $end
$var wire 1 B alu_src $end
$var wire 32 C alu_result [31:0] $end
$var wire 32 D alu_in2 [31:0] $end
$var wire 4 E alu_ctrl [3:0] $end
$scope module alu_inst $end
$var wire 32 F b [31:0] $end
$var wire 1 / zero $end
$var wire 4 G alu_ctrl [3:0] $end
$var wire 32 H a [31:0] $end
$var parameter 4 I ADD $end
$var parameter 4 J AND $end
$var parameter 4 K OR $end
$var parameter 4 L SLL $end
$var parameter 4 M SLT $end
$var parameter 4 N SLTU $end
$var parameter 4 O SRA $end
$var parameter 4 P SRL $end
$var parameter 4 Q SUB $end
$var parameter 4 R XOR $end
$var reg 32 S result [31:0] $end
$upscope $end
$scope module cu $end
$var wire 3 T func3 [2:0] $end
$var wire 7 U func7 [6:0] $end
$var wire 7 V opcode [6:0] $end
$var parameter 7 W BRANCH $end
$var parameter 7 X I_TYPE $end
$var parameter 7 Y LOAD $end
$var parameter 7 Z R_TYPE $end
$var parameter 7 [ STORE $end
$var reg 4 \ alu_ctrl [3:0] $end
$var reg 1 B alu_src $end
$var reg 1 A branch $end
$var reg 1 ; mem_read $end
$var reg 1 : mem_write $end
$var reg 1 3 reg_write $end
$upscope $end
$scope module dmem $end
$var wire 32 ] addr [31:0] $end
$var wire 1 ! clk $end
$var wire 1 ; mem_read $end
$var wire 1 : mem_write $end
$var wire 32 ^ data_out [31:0] $end
$var wire 32 _ data_in [31:0] $end
$upscope $end
$scope module imem $end
$var wire 1 ! clk $end
$var wire 32 ` instruction [31:0] $end
$var wire 32 a prog_addr [31:0] $end
$var wire 32 b prog_data [31:0] $end
$var wire 1 . prog_we $end
$var wire 32 c addr [31:0] $end
$upscope $end
$scope module imm_gen_inst $end
$var wire 32 d instr [31:0] $end
$var wire 7 e opcode [6:0] $end
$var parameter 7 f BRANCH $end
$var parameter 7 g I_TYPE $end
$var parameter 7 h LOAD $end
$var parameter 7 i STORE $end
$var reg 32 j imm [31:0] $end
$upscope $end
$scope module pc_inst $end
$var wire 1 ! clk $end
$var wire 32 k next_pc [31:0] $end
$var wire 1 " rst $end
$var reg 32 l pc [31:0] $end
$upscope $end
$scope module rf $end
$var wire 1 ! clk $end
$var wire 5 m rd [4:0] $end
$var wire 5 n rs1 [4:0] $end
$var wire 5 o rs2 [4:0] $end
$var wire 32 p wd [31:0] $end
$var wire 1 3 we $end
$var wire 32 q rd2 [31:0] $end
$var wire 32 r rd1 [31:0] $end
$upscope $end
$upscope $end
$upscope $end
$enddefinitions $end
$comment Show the parameter values. $end
$dumpall
b100011 i
b11 h
b10011 g
b1100011 f
b100011 [
b110011 Z
b11 Y
b10011 X
b1100011 W
b100 R
b1 Q
b110 P
b111 O
b1001 N
b1000 M
b101 L
b11 K
b10 J
b0 I
$end
#0
$dumpvars
b0 r
bx q
b101 p
b101 o
b0 n
b1 m
b0 l
b100 k
b101 j
b10011 e
b10100000000000010010011 d
b0 c
b0 b
b0 a
b10100000000000010010011 `
bx _
b0 ^
b101 ]
b0 \
b10011 V
b0 U
b0 T
b101 S
b0 H
b0 G
b101 F
b0 E
b101 D
b101 C
1B
0A
b0 @
b0 ?
b0 >
b101 =
b10100000000000010010011 <
0;
0:
b100 9
b10011 8
b0 7
b1 6
b0 5
bx 4
13
b0 2
b101 1
b101 0
0/
0.
b0 -
b0 ,
b101 +
1*
b1 )
b0 (
0'
bx &
b101 %
b10100000000000010010011 $
0#
1"
0!
$end
#5000
1!
#10000
0!
#15000
1#
0"
1!
#20000
0!
#25000
b11 +
b11 0
b11 p
b11 %
b11 C
b11 S
b11 ]
b11 D
b11 F
b11 =
b11 j
b10 )
b10 6
b10 m
b11 1
b11 o
b1100000000000100010011 $
b1100000000000100010011 <
b1100000000000100010011 `
b1100000000000100010011 d
b1000 9
b1000 k
b100 (
b100 7
b100 c
b100 l
1!
#30000
0!
#35000
b1000 +
b1000 0
b1000 p
b1000 %
b1000 C
b1000 S
b1000 ]
b11 &
b11 4
b11 _
b11 q
b101 5
b101 H
b101 r
0B
1*
13
b0 =
b0 j
b110011 e
b11 )
b11 6
b11 m
b10 1
b10 o
b1 2
b1 n
b110011 8
b110011 V
b1000001000000110110011 $
b1000001000000110110011 <
b1000001000000110110011 `
b1000001000000110110011 d
b1100 9
b1100 k
b1000 (
b1000 7
b1000 c
b1000 l
1!
#40000
0!
#45000
b101 +
b101 0
b101 p
b101 %
b101 C
b101 S
b101 ]
b1000 5
b1000 H
b1000 r
b1 E
b1 G
b1 \
1*
13
b100 )
b100 6
b100 m
b11 2
b11 n
b100000 >
b100000 U
b1000000001000011000001000110011 $
b1000000001000011000001000110011 <
b1000000001000011000001000110011 `
b1000000001000011000001000110011 d
b10000 9
b10000 k
b1100 (
b1100 7
b1100 c
b1100 l
1!
#50000
0!
#55000
1/
b0 +
b0 0
b0 p
b0 D
b0 F
b0 %
b0 C
b0 S
b0 ]
b1000 &
b1000 4
b1000 _
b1000 q
b0 5
b0 H
b0 r
1B
1'
1:
b0 E
b0 G
b0 \
0*
03
b100011 e
b0 )
b0 6
b0 m
b11 1
b11 o
b0 2
b0 n
b0 >
b0 U
b10 ?
b10 T
b100011 8
b100011 V
b1100000010000000100011 $
b1100000010000000100011 <
b1100000010000000100011 `
b1100000010000000100011 d
b10100 9
b10100 k
b10000 (
b10000 7
b10000 c
b10000 l
1!
#60000
0!
#65000
b1000 +
b1000 0
b1000 p
b1000 @
b1000 ^
b0 &
b0 4
b0 _
b0 q
1;
1*
13
1B
0'
0:
b11 e
b101 )
b101 6
b101 m
b0 1
b0 o
b11 8
b11 V
b10001010000011 $
b10001010000011 <
b10001010000011 `
b10001010000011 d
b11000 9
b11000 k
b10100 (
b10100 7
b10100 c
b10100 l
1!
#70000
0!
#75000
b0 @
b0 ^
b0 +
b0 0
b0 p
b1000 D
b1000 F
b1000 &
b1000 4
b1000 _
b1000 q
b1000 5
b1000 H
b1000 r
b1 E
b1 G
b1 \
1A
0B
0;
0*
03
b1000 =
b1000 j
b1100011 e
b1000 )
b1000 6
b1000 m
b11 1
b11 o
b101 2
b101 n
b0 ?
b0 T
b1100011 8
b1100011 V
b1100101000010001100011 $
b1100101000010001100011 <
b1100101000010001100011 `
b1100101000010001100011 d
b100000 9
b100000 k
b11000 (
b11000 7
b11000 c
b11000 l
1!
#80000
0!
#85000
b1001 +
b1001 0
b1001 p
b1001 D
b1001 F
0/
b1001 %
b1001 C
b1001 S
b1001 ]
bx &
bx 4
bx _
bx q
b0 5
b0 H
b0 r
1B
1*
13
b0 E
b0 G
b0 \
0A
b1001 =
b1001 j
b10011 e
b111 )
b111 6
b111 m
b1001 1
b1001 o
b0 2
b0 n
b10011 8
b10011 V
b100100000000001110010011 $
b100100000000001110010011 <
b100100000000001110010011 `
b100100000000001110010011 d
b100100 9
b100100 k
b100000 (
b100000 7
b100000 c
b100000 l
1!
#90000
0!
#95000
bx +
bx 0
bx p
x/
bx %
bx C
bx S
bx ]
bx D
bx F
bx 5
bx H
bx r
0B
0*
03
b0 =
b0 j
bx e
bx )
bx 6
bx m
bx 1
bx o
bx 2
bx n
bx >
bx U
bx ?
bx T
bx 8
bx V
bx $
bx <
bx `
bx d
b101000 9
b101000 k
b100100 (
b100100 7
b100100 c
b100100 l
1!
#100000
0!
#105000
b101100 9
b101100 k
b101000 (
b101000 7
b101000 c
b101000 l
1!
#110000
0!
#115000
b110000 9
b110000 k
b101100 (
b101100 7
b101100 c
b101100 l
1!
#120000
0!
#125000
b110100 9
b110100 k
b110000 (
b110000 7
b110000 c
b110000 l
1!
#130000
0!
#135000
b111000 9
b111000 k
b110100 (
b110100 7
b110100 c
b110100 l
1!
#140000
0!
#145000
b111100 9
b111100 k
b111000 (
b111000 7
b111000 c
b111000 l
1!
#150000
0!
#155000
b1000000 9
b1000000 k
b111100 (
b111100 7
b111100 c
b111100 l
1!
