rtl/memory/data_mem.v
module data_mem(
    input wire clk,              // Clock for synchronous writes
    input wire mem_read,         // Read enable (from control unit)
    input wire mem_write,        // Write enable (from control unit)
    input wire [2:0] store_type, // Store type: 000=byte(SB), 001=halfword(SH), 010=word(SW)
    input wire [31:0] addr,      // Memory address (byte-addressed)
    input wire [31:0] data_in,   // Data to write (from registers)

    output wire [31:0] data_out  // Data read from memory (to registers)
);

    // 256 × 32-bit data memory
    reg [31:0] mem [255:0];

    // Combinational read: output 0 if not reading
    assign data_out = (mem_read) ? mem[addr[9:2]] : 32'd0;

    // Synchronous write: selective byte writes based on store_type
    always @(posedge clk) begin
        if (mem_write) begin
            case (store_type)
                3'b000: begin // SB - Store Byte
                    case (addr[1:0])
                        2'b00: mem[addr[9:2]][7:0]   <= data_in[7:0];    // Byte 0
                        2'b01: mem[addr[9:2]][15:8]  <= data_in[7:0];    // Byte 1
                        2'b10: mem[addr[9:2]][23:16] <= data_in[7:0];    // Byte 2
                        2'b11: mem[addr[9:2]][31:24] <= data_in[7:0];    // Byte 3
                    endcase
                end
                3'b001: begin // SH - Store Halfword
                    case (addr[1])
                        1'b0: mem[addr[9:2]][15:0]  <= data_in[15:0];   // Halfword 0
                        1'b1: mem[addr[9:2]][31:16] <= data_in[15:0];   // Halfword 1
                    endcase
                end
                3'b010: begin // SW - Store Word
                    mem[addr[9:2]] <= data_in;                           // Full 32-bit word
                end
            endcase
        end
    end

endmodule

rtl/core/alu.v
module alu(
    input wire [31:0] a,
    input wire [31:0] b,
    input wire [3:0] alu_ctrl,
    output reg [31:0] result,
    output wire zero 
);

localparam ADD = 4'b0000;
localparam SUB = 4'b0001;
localparam AND = 4'b0010;
localparam OR  = 4'b0011;
localparam XOR = 4'b0100;
localparam SLL = 4'b0101;
localparam SRL = 4'b0110;
localparam SRA = 4'b0111;
localparam SLT = 4'b1000;
localparam SLTU = 4'b1001;

// Combinational logic: use blocking assignment (=) not non-blocking (<=)
// Blocking assignment ensures immediate evaluation (critical for combinational)
// Non-blocking (<=) would give stale values in combinational blocks

    always @(*) begin
        case (alu_ctrl)
            ADD: result = a + b;
            SUB: result = a - b;
            AND: result = a & b;
            OR: result = a | b; 
            XOR: result = a ^ b;
            // RV32 register and immediate shifts use only the low five bits.
            SLL: result = a << b[4:0];
            SRL: result = a >> b[4:0];
            SRA: result = $signed(a) >>> b[4:0];
            SLT: result = ($signed(a)<$signed(b)) ? 32'd1 : 32'd0;
            SLTU: result = (a<b) ? 32'd1 : 32'd0;
            default: result = 32'd0;
        endcase
    end

    assign zero = (result == 32'd0);
    
endmodule

rtl/imm_gen.v
module imm_gen(
    input wire [31:0] instr,
    output reg [31:0] imm
);
    wire [6:0] opcode = instr[6:0];

    localparam I_TYPE = 7'b0010011;
    localparam LOAD   = 7'b0000011;
    localparam STORE  = 7'b0100011;
    localparam BRANCH = 7'b1100011;

    always @(*) begin
        case (opcode)
            I_TYPE,
            LOAD:
                imm = {{20{instr[31]}}, instr[31:20]};

            STORE:
                imm = {{20{instr[31]}}, instr[31:25], instr[11:7]};

            BRANCH:
                imm = {{19{instr[31]}}, instr[31], instr[7],
                       instr[30:25], instr[11:8], 1'b0};

            default:
                imm = 32'd0;
        endcase
    end
endmodule

register_file.v
module register_file(
    input logic clk,
    input logic we,
    input logic [4:0] rs1,
    input logic [4:0] rs2,
    input logic [4:0] rd,
    input logic [31:0] wd,
    output logic [31:0] rd1,
    output logic [31:0] rd2
);

    logic [31:0] regfile [31:0];

    //for immidiate access of register file we used combinational/dataflow modelling.
    assign rd1 = regfile[rs1];
    assign rd2 = regfile[rs2];

    // since in write value is changing and output depends on state and input hence sequential unlike read.
    always_ff @(posedge clk) begin
        if(we && rd != 0)
            regfile[rd] <= wd;
    end

endmodule

rtl/control_unit.v
module control_unit(
    input wire [6:0] opcode,
    input wire [2:0] func3,
    input wire [6:0] func7,

    output reg reg_write,
    output reg mem_read,
    output reg mem_write,
    output reg [2:0] store_type,  // Store type: 000=SB, 001=SH, 010=SW
    output reg alu_src,
    output reg branch,
    output reg [2:0] branch_type,
    output reg [3:0] alu_ctrl
);
    localparam R_TYPE = 7'b0110011;    // Register-Register
    localparam I_TYPE = 7'b0010011;    // Immediate
    localparam LOAD   = 7'b0000011;    // Load
    localparam STORE  = 7'b0100011;    // Store
    localparam BRANCH = 7'b1100011;    // Branch

    always @(*) begin
        // Default: prevent latches
        reg_write = 0;
        mem_read = 0;
        mem_write = 0;
        store_type = 3'b010;  // Default to SW
        branch_type = 3'b000; // Default no branch
        alu_src = 0;
        branch = 0;
        alu_ctrl = 4'b0000;

        case (opcode)
            R_TYPE: begin
                reg_write = 1;
                case({func7, func3})
                    {7'b0000000, 3'b000}: alu_ctrl = 4'b0000;  // ADD
                    {7'b0100000, 3'b000}: alu_ctrl = 4'b0001;  // SUB
                    {7'b0000000, 3'b111}: alu_ctrl = 4'b0010;  // AND
                    {7'b0000000, 3'b110}: alu_ctrl = 4'b0011;  // OR
                    {7'b0000000, 3'b001}: alu_ctrl = 4'b0101;  // SLL
                    {7'b0000000, 3'b010}: alu_ctrl = 4'b1000;  // SLT
                    {7'b0000000, 3'b011}: alu_ctrl = 4'b1001;  // SLTU
                    {7'b0000000, 3'b100}: alu_ctrl = 4'b0100;  // XOR
                    {7'b0000000, 3'b101}: alu_ctrl = 4'b0110;  // SRL
                    {7'b0100000, 3'b101}: alu_ctrl = 4'b0111;  // SRA
                    default: alu_ctrl = 4'b1111;
                endcase
            end
            I_TYPE: begin
                reg_write = 1;
                alu_src = 1;
                case (func3)
                    3'b000: alu_ctrl = 4'b0000;  // ADDI
                    3'b010: alu_ctrl = 4'b1000;  // SLTI
                    3'b011: alu_ctrl = 4'b1001;  // SLTU
                    3'b100: alu_ctrl = 4'b0100;  // XORI
                    3'b110: alu_ctrl = 4'b0011;  // ORI
                    3'b111: alu_ctrl = 4'b0010;  // ANDI
                endcase
            end
            LOAD: begin
                reg_write = 1;
                mem_read = 1;
                alu_src = 1;
                alu_ctrl = 4'b0000;
                case (func3)
                    3'b000: begin // LB (sign-extend byte)
                    end
                    3'b001: begin // LH (sign-extend halfword)
                    end
                    3'b010: begin // LW (full word)
                    end
                    3'b100: begin // LBU (zero-extend byte)
                    end
                    3'b101: begin // LHU (zero-extend halfword)
                    end
                endcase
            end
            STORE: begin
                mem_write = 1;
                alu_src = 1;
                alu_ctrl = 4'b0000;
                case (func3)
                    3'b000: begin // SB (Store Byte)
                        store_type = 3'b000;
                    end
                    3'b001: begin // SH (Store Halfword)
                        store_type = 3'b001;
                    end
                    3'b010: begin // SW (Store Word)
                        store_type = 3'b010;
                    end
                endcase
            end
            BRANCH: begin
                branch = 1;
                case (func3)
                    3'b000: begin // BEQ
                        branch_type = 3'b000;
                        alu_ctrl = 4'b0001; // SUB
                    end
                    3'b001: begin // BNE
                        branch_type = 3'b001;
                        alu_ctrl = 4'b0001; // SUB
                    end
                    3'b100: begin // BLT
                        branch_type = 3'b010;
                        alu_ctrl = 4'b1000; // SLT
                    end
                    3'b101: begin // BGE
                        branch_type = 3'b011;
                        alu_ctrl = 4'b1000; // SLT
                    end
                    3'b110: begin // BLTU
                        branch_type = 3'b100;
                        alu_ctrl = 4'b1001; // SLTU
                    end
                    3'b111: begin // BGEU
                        branch_type = 3'b101;
                        alu_ctrl = 4'b1001; // SLTU
                    end
                endcase
            end
        endcase
    end

endmodule

rtl/mem.v
module inst_mem(
    input wire clk,
    input wire [31:0] addr,
    output wire [31:0] instruction
    // Add programing Interface
    input wire [31:0] prog_addr,
    input wire [31:0] prog_data,
    input wire        prog_we
);
    reg [31:0] mem [255:0];

    always @(posedge clk) begin
        if(prog_we)
            mem[prog_addr] <= prog_data;
    end
    // addr[9:2] converts byte address to word index
    assign instruction = mem[addr[9:2]];

endmodule

rtl/pc_rtl.v
module pc (
    input logic clk,
    input logic rst,
    input logic [31:0] next_pc,
    output logic [31:0] pc
);
    always @(posedge clk or posedge rst) begin
        if(rst)
            pc <= 0;
        else
            pc <= next_pc;
    end

endmodule

rtl/riscv_core.v
module riscv_core(
    input wire clk,
    input wire reset,
    // Add programing Interface
    input wire [31:0] prog_addr,
    input wire [31:0] prog_data,
    input wire        prog_we,

    output wire [31:0] dbg_pc,
    output wire [31:0] dbg_instr,
    output wire        dbg_reg_write,
    output wire [4:0]  dbg_rd,
    output wire [31:0] dbg_writeback_data,
    output wire        dbg_mem_write,
    output wire [31:0] dbg_mem_addr,
    output wire [31:0] dbg_mem_wdata,
    output wire        dbg_commit_valid
);

    //----------------------PC-----------------------
    wire [31:0] pc, next_pc;

    pc pc_inst (
        .clk(clk),
        .rst(reset),
        .next_pc(next_pc),
        .pc(pc)
    );

    //-------------------Instruction Memory----------
    wire [31:0] instr;
    inst_mem imem(
        .clk(clk),
        .addr(pc),
        .instruction(instr),
        .prog_addr(prog_addr),
        .prog_data(prog_data),
        .prog_we(prog_we)
    );

    //-----------------DECODE-----------------------
    wire [6:0] opcode;
    wire [2:0] func3;
    wire [6:0] func7;

    assign opcode = instr[6:0];
    assign func3 = instr[14:12];
    assign func7 = instr[31:25];

    //----------------Control Unit-----------------
    wire reg_write, mem_read, mem_write, alu_src, branch;
    wire [2:0] branch_type;
    wire [3:0] alu_ctrl;
    wire [2:0] store_type;

    control_unit cu (
        .opcode(opcode),
        .func3(func3),
        .func7(func7),
        .reg_write(reg_write),
        .mem_read(mem_read),
        .mem_write(mem_write),
        .store_type(store_type),
        .alu_src(alu_src),
        .branch(branch),
        .branch_type(branch_type),
        .alu_ctrl(alu_ctrl)
    );

    // -------------------- Register File --------------------
    wire [4:0] rs1, rs2, rd;
    wire [31:0] rd1, rd2, write_data;

    assign rs1 = instr[19:15];
    assign rs2 = instr[24:20];
    assign rd  = instr[11:7];

    register_file rf (
        .clk(clk),
        .we(reg_write),
        .rs1(rs1),
        .rs2(rs2),
        .rd(rd),
        .wd(write_data),
        .rd1(rd1),
        .rd2(rd2)
    );

    // -------------------- Immediate Generator --------------------
    wire [31:0] imm;

    imm_gen imm_gen_inst (
        .instr(instr),
        .imm(imm)
    );

    // -------------------- ALU --------------------
    wire [31:0] alu_in2, alu_result;
    wire zero;

    assign alu_in2 = (alu_src) ? imm : rd2;

    alu alu_inst (
        .a(rd1),
        .b(alu_in2),
        .alu_ctrl(alu_ctrl),
        .result(alu_result),
        .zero(zero)
    );

    // -------------------- Data Memory --------------------
    wire [31:0] data_out;

    data_mem dmem (
        .clk(clk),
        .mem_read(mem_read),
        .mem_write(mem_write),
        .store_type(store_type),
        .addr(alu_result),
        .data_in(rd2),
        .data_out(data_out)
    );

// -------------------- Load Data Extraction & Sign Extension --------------------
wire [31:0] load_data;

assign load_data = 
    (func3 == 3'b000) ? {{24{data_out[7]}},   data_out[7:0]}    : // LB  (sign-extend byte)
    (func3 == 3'b001) ? {{16{data_out[15]}},  data_out[15:0]}   : // LH  (sign-extend halfword)
    (func3 == 3'b100) ? {24'b0,               data_out[7:0]}    : // LBU (zero-extend byte)
    (func3 == 3'b101) ? {16'b0,               data_out[15:0]}   : // LHU (zero-extend halfword)
                        data_out;                                   // LW (full 32-bit word)

// -------------------- Write Back --------------------
assign write_data = (mem_read) ? load_data : alu_result;      //for LOAD write_data = load_data (with sign/zero extension) and for arithmetic operation write_data = alu_result

// -------------------- Branch Decision --------------------
wire branch_taken;

assign branch_taken = branch && (
    (branch_type == 3'b000 && alu_result == 32'd0) || // BEQ
    (branch_type == 3'b001 && alu_result != 32'd0) || // BNE
    (branch_type == 3'b010 && alu_result == 32'd1) || // BLT
    (branch_type == 3'b011 && alu_result == 32'd0) || // BGE
    (branch_type == 3'b100 && alu_result == 32'd1) || // BLTU
    (branch_type == 3'b101 && alu_result == 32'd0)    // BGEU
);

// -------------------- PC Update --------------------
assign next_pc = (branch_taken) ? pc + imm : pc + 4;       // branch is output of cu

// -------------------- Debug/Verification Interface --------------------
assign dbg_pc = pc;
assign dbg_instr = instr;
assign dbg_reg_write = reg_write;
assign dbg_rd = rd;
assign dbg_writeback_data = write_data;
assign dbg_mem_write = mem_write;
assign dbg_mem_addr = alu_result;
assign dbg_mem_wdata = rd2;
assign dbg_commit_valid = !reset && !prog_we;
    
endmodule

tb/tb_riscv_core.v
`timescale 1ns/1ps

module tb_riscv_core;
    
    // Testbench signals
    reg clk;
    reg reset;
    
    // Instantiate your RISC-V core
    riscv_core dut (
        .clk(clk),
        .reset(reset),
        .prog_addr(32'd0),
        .prog_data(32'd0),
        .prog_we(1'b0)
    );
    
    // Clock generation: 10ns period (100MHz)
    initial clk = 0;
    always #5 clk = ~clk;
    
    // Test program
    initial begin
        // Setup waveform dump
        $dumpfile("riscv.vcd");
        $dumpvars(0, tb_riscv_core);
        
        // Initialize instruction memory with program
        // Program:
        //   addi x1, x0, 5    -> x1 = 5
        //   addi x2, x0, 3    -> x2 = 3
        //   add  x3, x1, x2   -> x3 = 8
        //   sub  x4, x3, x2   -> x4 = 5
        //   sw   x3, 0(x0)    -> mem[0] = 8
        //   lw   x5, 0(x0)    -> x5 = 8
        //   beq  x5, x3, +8   -> skip next instruction
        //   addi x6, x0, 1    -> skipped
        //   addi x7, x0, 9    -> x7 = 9
        //   lb   x11, 4(x0)   -> x11 = -120 (sign-extended 0x88)
        //   lbu  x12, 4(x0)   -> x12 = 136 (zero-extended 0x88)
        //   lh   x13, 4(x0)   -> x13 = -30584 (sign-extended 0x8888)
        //   lhu  x14, 4(x0)   -> x14 = 34952 (zero-extended 0x8888)
        //   sb   x1, 8(x0)    -> mem[2][7:0] = 5 (byte store)
        //   sh   x2, 10(x0)   -> mem[2][31:16] = 3 (halfword store)
        //   lw   x15, 8(x0)   -> x15 = read back from mem[2]
        
        dut.imem.mem[0] = 32'h00500093;  // addi x1, x0, 5
        dut.imem.mem[1] = 32'h00300113;  // addi x2, x0, 3
        dut.imem.mem[2] = 32'h002081b3;  // add  x3, x1, x2
      	dut.imem.mem[3] = 32'h40218233;  // sub  x4, x3, x2
        dut.imem.mem[4] = 32'h00302023;  // sw   x3, 0(x0)
        dut.imem.mem[5] = 32'h00002283;  // lw   x5, 0(x0)
        dut.imem.mem[6] = 32'h00328463;  // beq  x5, x3, +8
        dut.imem.mem[7] = 32'h00100313;  // addi x6, x0, 1 (skipped)
        dut.imem.mem[8] = 32'h00900393;  // addi x7, x0, 9
        dut.imem.mem[9] = 32'h00400583;  // lb   x11, 4(x0)   -> sign-extend byte
        dut.imem.mem[10] = 32'h00404603; // lbu  x12, 4(x0)   -> zero-extend byte
        dut.imem.mem[11] = 32'h00401683; // lh   x13, 4(x0)   -> sign-extend halfword
        dut.imem.mem[12] = 32'h00405703; // lhu  x14, 4(x0)   -> zero-extend halfword
        dut.imem.mem[13] = 32'h00100423; // sb   x1, 8(x0)    -> store byte 5 to mem[2][7:0]
        dut.imem.mem[14] = 32'h00201523; // sh   x2, 10(x0)   -> store halfword 3 to mem[2][31:16]
        dut.imem.mem[15] = 32'h00802783; // lw   x15, 8(x0)   -> load mem[2] back to verify
        
        dut.imem.mem[16] = 32'h00500813; // addi x16, x0, 5
        dut.imem.mem[17] = 32'h00300893; // addi x17, x0, 3
        dut.imem.mem[18] = 32'h0000913;  // addi x18, x0, 0 (initialize skipped target)
        dut.imem.mem[19] = 32'h0000a13;  // addi x20, x0, 0
        dut.imem.mem[20] = 32'h0000b13;  // addi x22, x0, 0
        dut.imem.mem[21] = 32'h0000c13;  // addi x24, x0, 0
        dut.imem.mem[22] = 32'h0000d13;  // addi x26, x0, 0
        dut.imem.mem[23] = 32'h1181463;  // bne x16, x17, +8 -> taken
        dut.imem.mem[24] = 32'h100913;   // addi x18, x0, 1 (skipped)
        dut.imem.mem[25] = 32'h200993;   // addi x19, x0, 2
        dut.imem.mem[26] = 32'h108c463;  // blt x17, x16, +8 -> taken
        dut.imem.mem[27] = 32'h100a13;   // addi x20, x0, 1 (skipped)
        dut.imem.mem[28] = 32'h200a93;   // addi x21, x0, 2
        dut.imem.mem[29] = 32'h1185463;  // bge x16, x17, +8 -> taken
        dut.imem.mem[30] = 32'h100b13;   // addi x22, x0, 1 (skipped)
        dut.imem.mem[31] = 32'h200b93;   // addi x23, x0, 2
        dut.imem.mem[32] = 32'h108e463;  // bltu x17, x16, +8 -> taken
        dut.imem.mem[33] = 32'h100c13;   // addi x24, x0, 1 (skipped)
        dut.imem.mem[34] = 32'h200c93;   // addi x25, x0, 2
        dut.imem.mem[35] = 32'h1187463;  // bgeu x16, x17, +8 -> taken
        dut.imem.mem[36] = 32'h100d13;   // addi x26, x0, 1 (skipped)
        dut.imem.mem[37] = 32'h200d93;   // addi x27, x0, 2
        
        // Pre-initialize data memory with test value for load instruction testing
        dut.dmem.mem[1] = 32'h00008888;  // Test value for LB, LBU, LH, LHU instructions
        dut.dmem.mem[2] = 32'h00000000;  // Initialize mem[2] for store instruction testing
        
        // Apply reset
        reset = 1;
        repeat (2) @(posedge clk);
        reset = 0;
        
        // Run for enough cycles (38 instructions, ~46 cycles)
        repeat (46) @(posedge clk);
        
        // Display results
        $display("\n========== Test Results ==========");
        $display("x1 = %0d (expected: 5)", dut.rf.regfile[1]);
        $display("x2 = %0d (expected: 3)", dut.rf.regfile[2]);
        $display("x3 = %0d (expected: 8)", dut.rf.regfile[3]);
        $display("x4 = %0d (expected: 5)", dut.rf.regfile[4]);
        $display("x5 = %0d (expected: 8)", dut.rf.regfile[5]);
        $display("x7 = %0d (expected: 9)", dut.rf.regfile[7]);
        $display("mem[0] = %0d (expected: 8)", dut.dmem.mem[0]);
        $display("\n--- Load Instruction Tests ---");
        $display("x11 (LB  0x88) = %d (expected: -120)", $signed(dut.rf.regfile[11][7:0]));
        $display("x12 (LBU 0x88) = %0d (expected: 136)", dut.rf.regfile[12][7:0]);
        $display("x13 (LH  0x8888) = %d (expected: -30584)", $signed(dut.rf.regfile[13][15:0]));
        $display("x14 (LHU 0x8888) = %0d (expected: 34952)", dut.rf.regfile[14][15:0]);
        $display("\n--- Store Instruction Tests ---");
        $display("mem[2] (SB + SH) = 0x%08x (expected: 0x00030005)", dut.dmem.mem[2]);
        $display("x15 (LW mem[2]) = 0x%08x (expected: 0x00030005)", dut.rf.regfile[15]);
        $display("\n--- Branch Instruction Tests ---");
        $display("x18 = %0d (expected: 0)", dut.rf.regfile[18]);
        $display("x19 = %0d (expected: 2)", dut.rf.regfile[19]);
        $display("x20 = %0d (expected: 0)", dut.rf.regfile[20]);
        $display("x21 = %0d (expected: 2)", dut.rf.regfile[21]);
        $display("x22 = %0d (expected: 0)", dut.rf.regfile[22]);
        $display("x23 = %0d (expected: 2)", dut.rf.regfile[23]);
        $display("x24 = %0d (expected: 0)", dut.rf.regfile[24]);
        $display("x25 = %0d (expected: 2)", dut.rf.regfile[25]);
        $display("x26 = %0d (expected: 0)", dut.rf.regfile[26]);
        $display("x27 = %0d (expected: 2)", dut.rf.regfile[27]);
        $display("==================================\n");
        
        // Check if test passed
        if (dut.rf.regfile[1] == 5 &&
            dut.rf.regfile[2] == 3 &&
            dut.rf.regfile[3] == 8 &&
            dut.rf.regfile[4] == 5 &&
            dut.rf.regfile[5] == 8 &&
            dut.rf.regfile[7] == 9 &&
            dut.dmem.mem[0] == 8 &&
            $signed(dut.rf.regfile[11]) == -120 &&
            dut.rf.regfile[12][7:0] == 136 &&
            $signed(dut.rf.regfile[13]) == -30584 &&
            dut.rf.regfile[14][15:0] == 34952 &&
            dut.dmem.mem[2] == 32'h00030005 &&
            dut.rf.regfile[15] == 32'h00030005 &&
            dut.rf.regfile[18] == 0 &&
            dut.rf.regfile[19] == 2 &&
            dut.rf.regfile[20] == 0 &&
            dut.rf.regfile[21] == 2 &&
            dut.rf.regfile[22] == 0 &&
            dut.rf.regfile[23] == 2 &&
            dut.rf.regfile[24] == 0 &&
            dut.rf.regfile[25] == 2 &&
            dut.rf.regfile[26] == 0 &&
            dut.rf.regfile[27] == 2) begin
            $display("TEST PASSED!\n");
        end else begin
            $display("TEST FAILED!\n");
        end
        
        $finish;
    end
    
endmodule

riscv.vcd
$date
	Thu Jul  9 00:48:19 2026
$end
$version
	Icarus Verilog
$end
$timescale
	1ps
$end
$scope module tb_riscv_core $end
$var reg 1 ! clk $end
$var reg 1 " reset $end
$scope module dut $end
$var wire 1 # branch_taken $end
$var wire 1 ! clk $end
$var wire 1 $ dbg_commit_valid $end
$var wire 32 % dbg_instr [31:0] $end
$var wire 32 & dbg_mem_addr [31:0] $end
$var wire 32 ' dbg_mem_wdata [31:0] $end
$var wire 1 ( dbg_mem_write $end
$var wire 32 ) dbg_pc [31:0] $end
$var wire 5 * dbg_rd [4:0] $end
$var wire 1 + dbg_reg_write $end
$var wire 32 , dbg_writeback_data [31:0] $end
$var wire 32 - prog_addr [31:0] $end
$var wire 32 . prog_data [31:0] $end
$var wire 1 / prog_we $end
$var wire 1 " reset $end
$var wire 1 0 zero $end
$var wire 32 1 write_data [31:0] $end
$var wire 3 2 store_type [2:0] $end
$var wire 5 3 rs2 [4:0] $end
$var wire 5 4 rs1 [4:0] $end
$var wire 1 5 reg_write $end
$var wire 32 6 rd2 [31:0] $end
$var wire 32 7 rd1 [31:0] $end
$var wire 5 8 rd [4:0] $end
$var wire 32 9 pc [31:0] $end
$var wire 7 : opcode [6:0] $end
$var wire 32 ; next_pc [31:0] $end
$var wire 1 < mem_write $end
$var wire 1 = mem_read $end
$var wire 32 > load_data [31:0] $end
$var wire 32 ? instr [31:0] $end
$var wire 32 @ imm [31:0] $end
$var wire 7 A func7 [6:0] $end
$var wire 3 B func3 [2:0] $end
$var wire 32 C data_out [31:0] $end
$var wire 3 D branch_type [2:0] $end
$var wire 1 E branch $end
$var wire 1 F alu_src $end
$var wire 32 G alu_result [31:0] $end
$var wire 32 H alu_in2 [31:0] $end
$var wire 4 I alu_ctrl [3:0] $end
$scope module alu_inst $end
$var wire 32 J b [31:0] $end
$var wire 1 0 zero $end
$var wire 4 K alu_ctrl [3:0] $end
$var wire 32 L a [31:0] $end
$var parameter 4 M ADD $end
$var parameter 4 N AND $end
$var parameter 4 O OR $end
$var parameter 4 P SLL $end
$var parameter 4 Q SLT $end
$var parameter 4 R SLTU $end
$var parameter 4 S SRA $end
$var parameter 4 T SRL $end
$var parameter 4 U SUB $end
$var parameter 4 V XOR $end
$var reg 32 W result [31:0] $end
$upscope $end
$scope module cu $end
$var wire 3 X func3 [2:0] $end
$var wire 7 Y func7 [6:0] $end
$var wire 7 Z opcode [6:0] $end
$var parameter 7 [ BRANCH $end
$var parameter 7 \ I_TYPE $end
$var parameter 7 ] LOAD $end
$var parameter 7 ^ R_TYPE $end
$var parameter 7 _ STORE $end
$var reg 4 ` alu_ctrl [3:0] $end
$var reg 1 F alu_src $end
$var reg 1 E branch $end
$var reg 3 a branch_type [2:0] $end
$var reg 1 = mem_read $end
$var reg 1 < mem_write $end
$var reg 1 5 reg_write $end
$var reg 3 b store_type [2:0] $end
$upscope $end
$scope module dmem $end
$var wire 32 c addr [31:0] $end
$var wire 1 ! clk $end
$var wire 1 = mem_read $end
$var wire 1 < mem_write $end
$var wire 3 d store_type [2:0] $end
$var wire 32 e data_out [31:0] $end
$var wire 32 f data_in [31:0] $end
$upscope $end
$scope module imem $end
$var wire 1 ! clk $end
$var wire 32 g instruction [31:0] $end
$var wire 32 h prog_addr [31:0] $end
$var wire 32 i prog_data [31:0] $end
$var wire 1 / prog_we $end
$var wire 32 j addr [31:0] $end
$upscope $end
$scope module imm_gen_inst $end
$var wire 32 k instr [31:0] $end
$var wire 7 l opcode [6:0] $end
$var parameter 7 m BRANCH $end
$var parameter 7 n I_TYPE $end
$var parameter 7 o LOAD $end
$var parameter 7 p STORE $end
$var reg 32 q imm [31:0] $end
$upscope $end
$scope module pc_inst $end
$var wire 1 ! clk $end
$var wire 32 r next_pc [31:0] $end
$var wire 1 " rst $end
$var reg 32 s pc [31:0] $end
$upscope $end
$scope module rf $end
$var wire 1 ! clk $end
$var wire 5 t rd [4:0] $end
$var wire 5 u rs1 [4:0] $end
$var wire 5 v rs2 [4:0] $end
$var wire 32 w wd [31:0] $end
$var wire 1 5 we $end
$var wire 32 x rd2 [31:0] $end
$var wire 32 y rd1 [31:0] $end
$upscope $end
$upscope $end
$upscope $end
$enddefinitions $end
$comment Show the parameter values. $end
$dumpall
b100011 p
b11 o
b10011 n
b1100011 m
b100011 _
b110011 ^
b11 ]
b10011 \
b1100011 [
b100 V
b1 U
b110 T
b111 S
b1001 R
b1000 Q
b101 P
b11 O
b10 N
b0 M
$end
#0
$dumpvars
b0 y
bx x
b101 w
b101 v
b0 u
b1 t
b0 s
b100 r
b101 q
b10011 l
b10100000000000010010011 k
b0 j
b0 i
b0 h
b10100000000000010010011 g
bx f
b0 e
b10 d
b101 c
b10 b
b0 a
b0 `
b10011 Z
b0 Y
b0 X
b101 W
b0 L
b0 K
b101 J
b0 I
b101 H
b101 G
1F
0E
b0 D
b0 C
b0 B
b0 A
b101 @
b10100000000000010010011 ?
b0 >
0=
0<
b100 ;
b10011 :
b0 9
b1 8
b0 7
bx 6
15
b0 4
b101 3
b10 2
b101 1
00
0/
b0 .
b0 -
b101 ,
1+
b1 *
b0 )
0(
bx '
b101 &
b10100000000000010010011 %
0$
0#
1"
0!
$end
#5000
1!
#10000
0!
#15000
1$
0"
1!
#20000
0!
#25000
b11 ,
b11 1
b11 w
b11 &
b11 G
b11 W
b11 c
b11 H
b11 J
b11 @
b11 q
b10 *
b10 8
b10 t
b11 3
b11 v
b1100000000000100010011 %
b1100000000000100010011 ?
b1100000000000100010011 g
b1100000000000100010011 k
b1000 ;
b1000 r
b100 )
b100 9
b100 j
b100 s
1!
#30000
0!
#35000
b1000 ,
b1000 1
b1000 w
b1000 &
b1000 G
b1000 W
b1000 c
b11 '
b11 6
b11 f
b11 x
b101 7
b101 L
b101 y
0F
1+
15
b0 @
b0 q
b110011 l
b11 *
b11 8
b11 t
b10 3
b10 v
b1 4
b1 u
b110011 :
b110011 Z
b1000001000000110110011 %
b1000001000000110110011 ?
b1000001000000110110011 g
b1000001000000110110011 k
b1100 ;
b1100 r
b1000 )
b1000 9
b1000 j
b1000 s
1!
#40000
0!
#45000
b101 ,
b101 1
b101 w
b101 &
b101 G
b101 W
b101 c
b1000 7
b1000 L
b1000 y
b1 I
b1 K
b1 `
1+
15
b100 *
b100 8
b100 t
b11 4
b11 u
b100000 A
b100000 Y
b1000000001000011000001000110011 %
b1000000001000011000001000110011 ?
b1000000001000011000001000110011 g
b1000000001000011000001000110011 k
b10000 ;
b10000 r
b1100 )
b1100 9
b1100 j
b1100 s
1!
#50000
0!
#55000
10
b0 ,
b0 1
b0 w
b0 H
b0 J
b0 &
b0 G
b0 W
b0 c
b1000 '
b1000 6
b1000 f
b1000 x
b0 7
b0 L
b0 y
1F
1(
1<
b0 I
b0 K
b0 `
0+
05
b100011 l
b0 *
b0 8
b0 t
b11 3
b11 v
b0 4
b0 u
b0 A
b0 Y
b10 B
b10 X
b100011 :
b100011 Z
b1100000010000000100011 %
b1100000010000000100011 ?
b1100000010000000100011 g
b1100000010000000100011 k
b10100 ;
b10100 r
b10000 )
b10000 9
b10000 j
b10000 s
1!
#60000
0!
#65000
b1000 ,
b1000 1
b1000 w
b1000 >
b1000 C
b1000 e
b0 '
b0 6
b0 f
b0 x
1=
1+
15
1F
0(
0<
b11 l
b101 *
b101 8
b101 t
b0 3
b0 v
b11 :
b11 Z
b10001010000011 %
b10001010000011 ?
b10001010000011 g
b10001010000011 k
b11000 ;
b11000 r
b10100 )
b10100 9
b10100 j
b10100 s
1!
#70000
0!
#75000
b0 >
1#
b0 C
b0 e
b0 ,
b0 1
b0 w
b1000 H
b1000 J
b1000 '
b1000 6
b1000 f
b1000 x
b1000 7
b1000 L
b1000 y
b1 I
b1 K
b1 `
1E
0F
0=
0+
05
b1000 @
b1000 q
b1100011 l
b1000 *
b1000 8
b1000 t
b11 3
b11 v
b101 4
b101 u
b0 B
b0 X
b1100011 :
b1100011 Z
b1100101000010001100011 %
b1100101000010001100011 ?
b1100101000010001100011 g
b1100101000010001100011 k
b100000 ;
b100000 r
b11000 )
b11000 9
b11000 j
b11000 s
1!
#80000
0!
#85000
b1001 ,
b1001 1
b1001 w
b1001 H
b1001 J
00
b1001 &
b1001 G
b1001 W
b1001 c
0#
bx '
bx 6
bx f
bx x
b0 7
b0 L
b0 y
1F
1+
15
b0 I
b0 K
b0 `
0E
b1001 @
b1001 q
b10011 l
b111 *
b111 8
b111 t
b1001 3
b1001 v
b0 4
b0 u
b10011 :
b10011 Z
b100100000000001110010011 %
b100100000000001110010011 ?
b100100000000001110010011 g
b100100000000001110010011 k
b100100 ;
b100100 r
b100000 )
b100000 9
b100000 j
b100000 s
1!
#90000
0!
#95000
b11111111111111111111111110001000 >
b1000100010001000 C
b1000100010001000 e
b100 &
b100 G
b100 W
b100 c
b11111111111111111111111110001000 ,
b11111111111111111111111110001000 1
b11111111111111111111111110001000 w
b100 H
b100 J
b101 '
b101 6
b101 f
b101 x
1=
1F
1+
15
b100 @
b100 q
b11 l
b1011 *
b1011 8
b1011 t
b100 3
b100 v
b11 :
b11 Z
b10000000000010110000011 %
b10000000000010110000011 ?
b10000000000010110000011 g
b10000000000010110000011 k
b101000 ;
b101000 r
b100100 )
b100100 9
b100100 j
b100100 s
1!
#100000
0!
#105000
b10001000 ,
b10001000 1
b10001000 w
b10001000 >
1F
1=
1+
15
b1100 *
b1100 8
b1100 t
b100 B
b100 X
b10000000100011000000011 %
b10000000100011000000011 ?
b10000000100011000000011 g
b10000000100011000000011 k
b101100 ;
b101100 r
b101000 )
b101000 9
b101000 j
b101000 s
1!
#110000
0!
