rtl/memory/data_mem.v
module data_mem(
    input wire clk,              // Clock for synchronous writes
    input wire mem_read,         // Read enable (from control unit)
    input wire mem_write,        // Write enable (from control unit)
    input wire [2:0] store_type, // Store type: 000=byte(SB), 001=halfword(SH), 010=word(SW)
    input wire [31:0] addr,      // Memory address (byte-addressed)
    input wire [31:0] data_in,   // Data to write (from registers)

    output wire [31:0] data_out  // Data read from memory (to registers)
);

    // 256 × 32-bit data memory
    reg [31:0] mem [255:0];

    // Combinational read: output 0 if not reading
    assign data_out = (mem_read) ? mem[addr[9:2]] : 32'd0;

    // Synchronous write: selective byte writes based on store_type
    always @(posedge clk) begin
        if (mem_write) begin
            case (store_type)
                3'b000: begin // SB - Store Byte
                    case (addr[1:0])
                        2'b00: mem[addr[9:2]][7:0]   <= data_in[7:0];    // Byte 0
                        2'b01: mem[addr[9:2]][15:8]  <= data_in[7:0];    // Byte 1
                        2'b10: mem[addr[9:2]][23:16] <= data_in[7:0];    // Byte 2
                        2'b11: mem[addr[9:2]][31:24] <= data_in[7:0];    // Byte 3
                    endcase
                end
                3'b001: begin // SH - Store Halfword
                    case (addr[1])
                        1'b0: mem[addr[9:2]][15:0]  <= data_in[15:0];   // Halfword 0
                        1'b1: mem[addr[9:2]][31:16] <= data_in[15:0];   // Halfword 1
                    endcase
                end
                3'b010: begin // SW - Store Word
                    mem[addr[9:2]] <= data_in;                           // Full 32-bit word
                end
            endcase
        end
    end

endmodule

rtl/core/alu.v
module alu(
    input wire [31:0] a,
    input wire [31:0] b,
    input wire [3:0] alu_ctrl,
    output reg [31:0] result,
    output wire zero 
);

localparam ADD = 4'b0000;
localparam SUB = 4'b0001;
localparam AND = 4'b0010;
localparam OR  = 4'b0011;
localparam XOR = 4'b0100;
localparam SLL = 4'b0101;
localparam SRL = 4'b0110;
localparam SRA = 4'b0111;
localparam SLT = 4'b1000;
localparam SLTU = 4'b1001;

// Combinational logic: use blocking assignment (=) not non-blocking (<=)
// Blocking assignment ensures immediate evaluation (critical for combinational)
// Non-blocking (<=) would give stale values in combinational blocks

    always @(*) begin
        case (alu_ctrl)
            ADD: result = a + b;
            SUB: result = a - b;
            AND: result = a & b;
            OR: result = a | b; 
            XOR: result = a ^ b;
            // RV32 register and immediate shifts use only the low five bits.
            SLL: result = a << b[4:0];
            SRL: result = a >> b[4:0];
            SRA: result = $signed(a) >>> b[4:0];
            SLT: result = ($signed(a)<$signed(b)) ? 32'd1 : 32'd0;
            SLTU: result = (a<b) ? 32'd1 : 32'd0;
            default: result = 32'd0;
        endcase
    end

    assign zero = (result == 32'd0);
    
endmodule

rtl/imm_gen.v
module imm_gen(
    input wire [31:0] instr,
    output reg [31:0] imm
);
    wire [6:0] opcode = instr[6:0];

    localparam I_TYPE = 7'b0010011;
    localparam LOAD   = 7'b0000011;
    localparam STORE  = 7'b0100011;
    localparam BRANCH = 7'b1100011;

    always @(*) begin
        case (opcode)
            I_TYPE,
            LOAD:
                imm = {{20{instr[31]}}, instr[31:20]};

            STORE:
                imm = {{20{instr[31]}}, instr[31:25], instr[11:7]};

            BRANCH:
                imm = {{19{instr[31]}}, instr[31], instr[7],
                       instr[30:25], instr[11:8], 1'b0};

            default:
                imm = 32'd0;
        endcase
    end
endmodule

register_file.v
module register_file(
    input logic clk,
    input logic we,
    input logic [4:0] rs1,
    input logic [4:0] rs2,
    input logic [4:0] rd,
    input logic [31:0] wd,
    output logic [31:0] rd1,
    output logic [31:0] rd2
);

    logic [31:0] regfile [31:0];

    //for immidiate access of register file we used combinational/dataflow modelling.
    assign rd1 = regfile[rs1];
    assign rd2 = regfile[rs2];

    // since in write value is changing and output depends on state and input hence sequential unlike read.
    always_ff @(posedge clk) begin
        if(we && rd != 0)
            regfile[rd] <= wd;
    end

endmodule

rtl/control_unit.v
module control_unit(
    input wire [6:0] opcode,
    input wire [2:0] func3,
    input wire [6:0] func7,

    output reg reg_write,
    output reg mem_read,
    output reg mem_write,
    output reg [2:0] store_type,  // Store type: 000=SB, 001=SH, 010=SW
    output reg alu_src,
    output reg branch,
    output reg [3:0] alu_ctrl
);
    localparam R_TYPE = 7'b0110011;    // Register-Register
    localparam I_TYPE = 7'b0010011;    // Immediate
    localparam LOAD   = 7'b0000011;    // Load
    localparam STORE  = 7'b0100011;    // Store
    localparam BRANCH = 7'b1100011;    // Branch

    always @(*) begin
        // Default: prevent latches
        reg_write = 0;
        mem_read = 0;
        mem_write = 0;
        store_type = 3'b010;  // Default to SW
        alu_src = 0;
        branch = 0;
        alu_ctrl = 4'b0000;

        case (opcode)
            R_TYPE: begin
                reg_write = 1;
                case({func7, func3})
                    {7'b0000000, 3'b000}: alu_ctrl = 4'b0000;  // ADD
                    {7'b0100000, 3'b000}: alu_ctrl = 4'b0001;  // SUB
                    {7'b0000000, 3'b111}: alu_ctrl = 4'b0010;  // AND
                    {7'b0000000, 3'b110}: alu_ctrl = 4'b0011;  // OR
                    {7'b0000000, 3'b001}: alu_ctrl = 4'b0101;  // SLL
                    {7'b0000000, 3'b010}: alu_ctrl = 4'b1000;  // SLT
                    {7'b0000000, 3'b011}: alu_ctrl = 4'b1001;  // SLTU
                    {7'b0000000, 3'b100}: alu_ctrl = 4'b0100;  // XOR
                    {7'b0000000, 3'b101}: alu_ctrl = 4'b0110;  // SRL
                    {7'b0100000, 3'b101}: alu_ctrl = 4'b0111;  // SRA
                    default: alu_ctrl = 4'b1111;
                endcase
            end
            I_TYPE: begin
                reg_write = 1;
                alu_src = 1;
                case (func3)
                    3'b000: alu_ctrl = 4'b0000;  // ADDI
                    3'b010: alu_ctrl = 4'b1000;  // SLTI
                    3'b011: alu_ctrl = 4'b1001;  // SLTU
                    3'b100: alu_ctrl = 4'b0100;  // XORI
                    3'b110: alu_ctrl = 4'b0011;  // ORI
                    3'b111: alu_ctrl = 4'b0010;  // ANDI
                endcase
            end
            LOAD: begin
                reg_write = 1;
                mem_read = 1;
                alu_src = 1;
                alu_ctrl = 4'b0000;
                case (func3)
                    3'b000: begin // LB (sign-extend byte)
                    end
                    3'b001: begin // LH (sign-extend halfword)
                    end
                    3'b010: begin // LW (full word)
                    end
                    3'b100: begin // LBU (zero-extend byte)
                    end
                    3'b101: begin // LHU (zero-extend halfword)
                    end
                endcase
            end
            STORE: begin
                mem_write = 1;
                alu_src = 1;
                alu_ctrl = 4'b0000;
                case (func3)
                    3'b000: begin // SB (Store Byte)
                        store_type = 3'b000;
                    end
                    3'b001: begin // SH (Store Halfword)
                        store_type = 3'b001;
                    end
                    3'b010: begin // SW (Store Word)
                        store_type = 3'b010;
                    end
                endcase
            end
            BRANCH: begin
                case (func3)
                    3'b000: begin // BEQ
                        branch = 1;
                        alu_ctrl = 4'b0001;
                    end
                endcase
            end
        endcase
    end

endmodule

rtl/mem.v
module inst_mem(
    input wire clk,
    input wire [31:0] addr,
    output wire [31:0] instruction
    // Add programing Interface
    input wire [31:0] prog_addr,
    input wire [31:0] prog_data,
    input wire        prog_we
);
    reg [31:0] mem [255:0];

    always @(posedge clk) begin
        if(prog_we)
            mem[prog_addr] <= prog_data;
    end
    // addr[9:2] converts byte address to word index
    assign instruction = mem[addr[9:2]];

endmodule

rtl/pc_rtl.v
module pc (
    input logic clk,
    input logic rst,
    input logic [31:0] next_pc,
    output logic [31:0] pc
);
    always @(posedge clk or posedge rst) begin
        if(rst)
            pc <= 0;
        else
            pc <= next_pc;
    end

endmodule

rtl/riscv_core.v
module riscv_core(
    input wire clk,
    input wire reset,
    // Add programing Interface
    input wire [31:0] prog_addr,
    input wire [31:0] prog_data,
    input wire        prog_we,

    output wire [31:0] dbg_pc,
    output wire [31:0] dbg_instr,
    output wire        dbg_reg_write,
    output wire [4:0]  dbg_rd,
    output wire [31:0] dbg_writeback_data,
    output wire        dbg_mem_write,
    output wire [31:0] dbg_mem_addr,
    output wire [31:0] dbg_mem_wdata,
    output wire        dbg_commit_valid
);

    //----------------------PC-----------------------
    wire [31:0] pc, next_pc;

    pc pc_inst (
        .clk(clk),
        .rst(reset),
        .next_pc(next_pc),
        .pc(pc)
    );

    //-------------------Instruction Memory----------
    wire [31:0] instr;
    inst_mem imem(
        .clk(clk),
        .addr(pc),
        .instruction(instr),
        .prog_addr(prog_addr),
        .prog_data(prog_data),
        .prog_we(prog_we)
    );

    //-----------------DECODE-----------------------
    wire [6:0] opcode;
    wire [2:0] func3;
    wire [6:0] func7;

    assign opcode = instr[6:0];
    assign func3 = instr[14:12];
    assign func7 = instr[31:25];

    //----------------Control Unit-----------------
    wire reg_write, mem_read, mem_write, alu_src, branch;
    wire [3:0] alu_ctrl;
    wire [2:0] store_type;

    control_unit cu (
        .opcode(opcode),
        .func3(func3),
        .func7(func7),
        .reg_write(reg_write),
        .mem_read(mem_read),
        .mem_write(mem_write),
        .store_type(store_type),
        .alu_src(alu_src),
        .branch(branch),
        .alu_ctrl(alu_ctrl)
    );

    // -------------------- Register File --------------------
    wire [4:0] rs1, rs2, rd;
    wire [31:0] rd1, rd2, write_data;

    assign rs1 = instr[19:15];
    assign rs2 = instr[24:20];
    assign rd  = instr[11:7];

    register_file rf (
        .clk(clk),
        .we(reg_write),
        .rs1(rs1),
        .rs2(rs2),
        .rd(rd),
        .wd(write_data),
        .rd1(rd1),
        .rd2(rd2)
    );

    // -------------------- Immediate Generator --------------------
    wire [31:0] imm;

    imm_gen imm_gen_inst (
        .instr(instr),
        .imm(imm)
    );

    // -------------------- ALU --------------------
    wire [31:0] alu_in2, alu_result;
    wire zero;

    assign alu_in2 = (alu_src) ? imm : rd2;

    alu alu_inst (
        .a(rd1),
        .b(alu_in2),
        .alu_ctrl(alu_ctrl),
        .result(alu_result),
        .zero(zero)
    );

    // -------------------- Data Memory --------------------
    wire [31:0] data_out;

    data_mem dmem (
        .clk(clk),
        .mem_read(mem_read),
        .mem_write(mem_write),
        .store_type(store_type),
        .addr(alu_result),
        .data_in(rd2),
        .data_out(data_out)
    );

// -------------------- Load Data Extraction & Sign Extension --------------------
wire [31:0] load_data;

assign load_data = 
    (func3 == 3'b000) ? {{24{data_out[7]}},   data_out[7:0]}    : // LB  (sign-extend byte)
    (func3 == 3'b001) ? {{16{data_out[15]}},  data_out[15:0]}   : // LH  (sign-extend halfword)
    (func3 == 3'b100) ? {24'b0,               data_out[7:0]}    : // LBU (zero-extend byte)
    (func3 == 3'b101) ? {16'b0,               data_out[15:0]}   : // LHU (zero-extend halfword)
                        data_out;                                   // LW (full 32-bit word)

// -------------------- Write Back --------------------
assign write_data = (mem_read) ? load_data : alu_result;      //for LOAD write_data = load_data (with sign/zero extension) and for arithmetic operation write_data = alu_result

// -------------------- PC Update --------------------
assign next_pc = (branch && zero) ? pc + imm : pc + 4;       // branch is output of cu

// -------------------- Debug/Verification Interface --------------------
assign dbg_pc = pc;
assign dbg_instr = instr;
assign dbg_reg_write = reg_write;
assign dbg_rd = rd;
assign dbg_writeback_data = write_data;
assign dbg_mem_write = mem_write;
assign dbg_mem_addr = alu_result;
assign dbg_mem_wdata = rd2;
assign dbg_commit_valid = !reset && !prog_we;
    
endmodule

tb/tb_riscv_core.v
`timescale 1ns/1ps

module tb_riscv_core;
    
    // Testbench signals
    reg clk;
    reg reset;
    
    // Instantiate your RISC-V core
    riscv_core dut (
        .clk(clk),
        .reset(reset),
        .prog_addr(32'd0),
        .prog_data(32'd0),
        .prog_we(1'b0)
    );
    
    // Clock generation: 10ns period (100MHz)
    initial clk = 0;
    always #5 clk = ~clk;
    
    // Test program
    initial begin
        // Setup waveform dump
        $dumpfile("riscv.vcd");
        $dumpvars(0, tb_riscv_core);
        
        // Initialize instruction memory with program
        // Program:
        //   addi x1, x0, 5    -> x1 = 5
        //   addi x2, x0, 3    -> x2 = 3
        //   add  x3, x1, x2   -> x3 = 8
        //   sub  x4, x3, x2   -> x4 = 5
        //   sw   x3, 0(x0)    -> mem[0] = 8
        //   lw   x5, 0(x0)    -> x5 = 8
        //   beq  x5, x3, +8   -> skip next instruction
        //   addi x6, x0, 1    -> skipped
        //   addi x7, x0, 9    -> x7 = 9
        //   lb   x11, 4(x0)   -> x11 = -120 (sign-extended 0x88)
        //   lbu  x12, 4(x0)   -> x12 = 136 (zero-extended 0x88)
        //   lh   x13, 4(x0)   -> x13 = -30584 (sign-extended 0x8888)
        //   lhu  x14, 4(x0)   -> x14 = 34952 (zero-extended 0x8888)
        //   sb   x1, 8(x0)    -> mem[2][7:0] = 5 (byte store)
        //   sh   x2, 10(x0)   -> mem[2][31:16] = 3 (halfword store)
        //   lw   x15, 8(x0)   -> x15 = read back from mem[2]
        
        dut.imem.mem[0] = 32'h00500093;  // addi x1, x0, 5
        dut.imem.mem[1] = 32'h00300113;  // addi x2, x0, 3
        dut.imem.mem[2] = 32'h002081b3;  // add  x3, x1, x2
      	dut.imem.mem[3] = 32'h40218233;  // sub  x4, x3, x2
        dut.imem.mem[4] = 32'h00302023;  // sw   x3, 0(x0)
        dut.imem.mem[5] = 32'h00002283;  // lw   x5, 0(x0)
        dut.imem.mem[6] = 32'h00328463;  // beq  x5, x3, +8
        dut.imem.mem[7] = 32'h00100313;  // addi x6, x0, 1 (skipped)
        dut.imem.mem[8] = 32'h00900393;  // addi x7, x0, 9
        dut.imem.mem[9] = 32'h00400583;  // lb   x11, 4(x0)   -> sign-extend byte
        dut.imem.mem[10] = 32'h00404603; // lbu  x12, 4(x0)   -> zero-extend byte
        dut.imem.mem[11] = 32'h00401683; // lh   x13, 4(x0)   -> sign-extend halfword
        dut.imem.mem[12] = 32'h00405703; // lhu  x14, 4(x0)   -> zero-extend halfword
        dut.imem.mem[13] = 32'h00100423; // sb   x1, 8(x0)    -> store byte 5 to mem[2][7:0]
        dut.imem.mem[14] = 32'h00201523; // sh   x2, 10(x0)   -> store halfword 3 to mem[2][31:16]
        dut.imem.mem[15] = 32'h00802783; // lw   x15, 8(x0)   -> load mem[2] back to verify
        
        // Pre-initialize data memory with test value for load instruction testing
        dut.dmem.mem[1] = 32'h00008888;  // Test value for LB, LBU, LH, LHU instructions
        dut.dmem.mem[2] = 32'h00000000;  // Initialize mem[2] for store instruction testing
        
        // Apply reset
        reset = 1;
        repeat (2) @(posedge clk);
        reset = 0;
        
        // Run for enough cycles (16 instructions, ~22-24 cycles)
        repeat (26) @(posedge clk);
        
        // Display results
        $display("\n========== Test Results ==========");
        $display("x1 = %0d (expected: 5)", dut.rf.regfile[1]);
        $display("x2 = %0d (expected: 3)", dut.rf.regfile[2]);
        $display("x3 = %0d (expected: 8)", dut.rf.regfile[3]);
        $display("x4 = %0d (expected: 5)", dut.rf.regfile[4]);
        $display("x5 = %0d (expected: 8)", dut.rf.regfile[5]);
        $display("x7 = %0d (expected: 9)", dut.rf.regfile[7]);
        $display("mem[0] = %0d (expected: 8)", dut.dmem.mem[0]);
        $display("\n--- Load Instruction Tests ---");
        $display("x11 (LB  0x88) = %d (expected: -120)", $signed(dut.rf.regfile[11][7:0]));
        $display("x12 (LBU 0x88) = %0d (expected: 136)", dut.rf.regfile[12][7:0]);
        $display("x13 (LH  0x8888) = %d (expected: -30584)", $signed(dut.rf.regfile[13][15:0]));
        $display("x14 (LHU 0x8888) = %0d (expected: 34952)", dut.rf.regfile[14][15:0]);
        $display("\n--- Store Instruction Tests ---");
        $display("mem[2] (SB + SH) = 0x%08x (expected: 0x00030005)", dut.dmem.mem[2]);
        $display("x15 (LW mem[2]) = 0x%08x (expected: 0x00030005)", dut.rf.regfile[15]);
        $display("==================================\n");
        
        // Check if test passed
        if (dut.rf.regfile[1] == 5 &&
            dut.rf.regfile[2] == 3 &&
            dut.rf.regfile[3] == 8 &&
            dut.rf.regfile[4] == 5 &&
            dut.rf.regfile[5] == 8 &&
            dut.rf.regfile[7] == 9 &&
            dut.dmem.mem[0] == 8 &&
            $signed(dut.rf.regfile[11]) == -120 &&
            dut.rf.regfile[12][7:0] == 136 &&
            $signed(dut.rf.regfile[13]) == -30584 &&
            dut.rf.regfile[14][15:0] == 34952 &&
            dut.dmem.mem[2] == 32'h00030005 &&
            dut.rf.regfile[15] == 32'h00030005) begin
            $display("TEST PASSED!\n");
        end else begin
            $display("TEST FAILED!\n");
        end
        
        $finish;
    end
    
endmodule

riscv.vcd
$date
	Wed Jul  8 22:14:11 2026
$end
$version
	Icarus Verilog
$end
$timescale
	1ps
$end
$scope module tb_riscv_core $end
$var reg 1 ! clk $end
$var reg 1 " reset $end
$scope module dut $end
$var wire 1 ! clk $end
$var wire 1 # dbg_commit_valid $end
$var wire 32 $ dbg_instr [31:0] $end
$var wire 32 % dbg_mem_addr [31:0] $end
$var wire 32 & dbg_mem_wdata [31:0] $end
$var wire 1 ' dbg_mem_write $end
$var wire 32 ( dbg_pc [31:0] $end
$var wire 5 ) dbg_rd [4:0] $end
$var wire 1 * dbg_reg_write $end
$var wire 32 + dbg_writeback_data [31:0] $end
$var wire 32 , prog_addr [31:0] $end
$var wire 32 - prog_data [31:0] $end
$var wire 1 . prog_we $end
$var wire 1 " reset $end
$var wire 1 / zero $end
$var wire 32 0 write_data [31:0] $end
$var wire 3 1 store_type [2:0] $end
$var wire 5 2 rs2 [4:0] $end
$var wire 5 3 rs1 [4:0] $end
$var wire 1 4 reg_write $end
$var wire 32 5 rd2 [31:0] $end
$var wire 32 6 rd1 [31:0] $end
$var wire 5 7 rd [4:0] $end
$var wire 32 8 pc [31:0] $end
$var wire 7 9 opcode [6:0] $end
$var wire 32 : next_pc [31:0] $end
$var wire 1 ; mem_write $end
$var wire 1 < mem_read $end
$var wire 32 = load_data [31:0] $end
$var wire 32 > instr [31:0] $end
$var wire 32 ? imm [31:0] $end
$var wire 7 @ func7 [6:0] $end
$var wire 3 A func3 [2:0] $end
$var wire 32 B data_out [31:0] $end
$var wire 1 C branch $end
$var wire 1 D alu_src $end
$var wire 32 E alu_result [31:0] $end
$var wire 32 F alu_in2 [31:0] $end
$var wire 4 G alu_ctrl [3:0] $end
$scope module alu_inst $end
$var wire 32 H b [31:0] $end
$var wire 1 / zero $end
$var wire 4 I alu_ctrl [3:0] $end
$var wire 32 J a [31:0] $end
$var parameter 4 K ADD $end
$var parameter 4 L AND $end
$var parameter 4 M OR $end
$var parameter 4 N SLL $end
$var parameter 4 O SLT $end
$var parameter 4 P SLTU $end
$var parameter 4 Q SRA $end
$var parameter 4 R SRL $end
$var parameter 4 S SUB $end
$var parameter 4 T XOR $end
$var reg 32 U result [31:0] $end
$upscope $end
$scope module cu $end
$var wire 3 V func3 [2:0] $end
$var wire 7 W func7 [6:0] $end
$var wire 7 X opcode [6:0] $end
$var parameter 7 Y BRANCH $end
$var parameter 7 Z I_TYPE $end
$var parameter 7 [ LOAD $end
$var parameter 7 \ R_TYPE $end
$var parameter 7 ] STORE $end
$var reg 4 ^ alu_ctrl [3:0] $end
$var reg 1 D alu_src $end
$var reg 1 C branch $end
$var reg 1 < mem_read $end
$var reg 1 ; mem_write $end
$var reg 1 4 reg_write $end
$var reg 3 _ store_type [2:0] $end
$upscope $end
$scope module dmem $end
$var wire 32 ` addr [31:0] $end
$var wire 1 ! clk $end
$var wire 1 < mem_read $end
$var wire 1 ; mem_write $end
$var wire 3 a store_type [2:0] $end
$var wire 32 b data_out [31:0] $end
$var wire 32 c data_in [31:0] $end
$upscope $end
$scope module imem $end
$var wire 1 ! clk $end
$var wire 32 d instruction [31:0] $end
$var wire 32 e prog_addr [31:0] $end
$var wire 32 f prog_data [31:0] $end
$var wire 1 . prog_we $end
$var wire 32 g addr [31:0] $end
$upscope $end
$scope module imm_gen_inst $end
$var wire 32 h instr [31:0] $end
$var wire 7 i opcode [6:0] $end
$var parameter 7 j BRANCH $end
$var parameter 7 k I_TYPE $end
$var parameter 7 l LOAD $end
$var parameter 7 m STORE $end
$var reg 32 n imm [31:0] $end
$upscope $end
$scope module pc_inst $end
$var wire 1 ! clk $end
$var wire 32 o next_pc [31:0] $end
$var wire 1 " rst $end
$var reg 32 p pc [31:0] $end
$upscope $end
$scope module rf $end
$var wire 1 ! clk $end
$var wire 5 q rd [4:0] $end
$var wire 5 r rs1 [4:0] $end
$var wire 5 s rs2 [4:0] $end
$var wire 32 t wd [31:0] $end
$var wire 1 4 we $end
$var wire 32 u rd2 [31:0] $end
$var wire 32 v rd1 [31:0] $end
$upscope $end
$upscope $end
$upscope $end
$enddefinitions $end
$comment Show the parameter values. $end
$dumpall
b100011 m
b11 l
b10011 k
b1100011 j
b100011 ]
b110011 \
b11 [
b10011 Z
b1100011 Y
b100 T
b1 S
b110 R
b111 Q
b1001 P
b1000 O
b101 N
b11 M
b10 L
b0 K
$end
#0
$dumpvars
b0 v
bx u
b101 t
b101 s
b0 r
b1 q
b0 p
b100 o
b101 n
b10011 i
b10100000000000010010011 h
b0 g
b0 f
b0 e
b10100000000000010010011 d
bx c
b0 b
b10 a
b101 `
b10 _
b0 ^
b10011 X
b0 W
b0 V
b101 U
b0 J
b0 I
b101 H
b0 G
b101 F
b101 E
1D
0C
b0 B
b0 A
b0 @
b101 ?
b10100000000000010010011 >
b0 =
0<
0;
b100 :
b10011 9
b0 8
b1 7
b0 6
bx 5
14
b0 3
b101 2
b10 1
b101 0
0/
0.
b0 -
b0 ,
b101 +
1*
b1 )
b0 (
0'
bx &
b101 %
b10100000000000010010011 $
0#
1"
0!
$end
#5000
1!
#10000
0!
#15000
1#
0"
1!
#20000
0!
#25000
b11 +
b11 0
b11 t
b11 %
b11 E
b11 U
b11 `
b11 F
b11 H
b11 ?
b11 n
b10 )
b10 7
b10 q
b11 2
b11 s
b1100000000000100010011 $
b1100000000000100010011 >
b1100000000000100010011 d
b1100000000000100010011 h
b1000 :
b1000 o
b100 (
b100 8
b100 g
b100 p
1!
#30000
0!
#35000
b1000 +
b1000 0
b1000 t
b1000 %
b1000 E
b1000 U
b1000 `
b11 &
b11 5
b11 c
b11 u
b101 6
b101 J
b101 v
0D
1*
14
b0 ?
b0 n
b110011 i
b11 )
b11 7
b11 q
b10 2
b10 s
b1 3
b1 r
b110011 9
b110011 X
b1000001000000110110011 $
b1000001000000110110011 >
b1000001000000110110011 d
b1000001000000110110011 h
b1100 :
b1100 o
b1000 (
b1000 8
b1000 g
b1000 p
1!
#40000
0!
#45000
b101 +
b101 0
b101 t
b101 %
b101 E
b101 U
b101 `
b1000 6
b1000 J
b1000 v
b1 G
b1 I
b1 ^
1*
14
b100 )
b100 7
b100 q
b11 3
b11 r
b100000 @
b100000 W
b1000000001000011000001000110011 $
b1000000001000011000001000110011 >
b1000000001000011000001000110011 d
b1000000001000011000001000110011 h
b10000 :
b10000 o
b1100 (
b1100 8
b1100 g
b1100 p
1!
#50000
0!
#55000
1/
b0 +
b0 0
b0 t
b0 F
b0 H
b0 %
b0 E
b0 U
b0 `
b1000 &
b1000 5
b1000 c
b1000 u
b0 6
b0 J
b0 v
1D
1'
1;
b0 G
b0 I
b0 ^
0*
04
b100011 i
b0 )
b0 7
b0 q
b11 2
b11 s
b0 3
b0 r
b0 @
b0 W
b10 A
b10 V
b100011 9
b100011 X
b1100000010000000100011 $
b1100000010000000100011 >
b1100000010000000100011 d
b1100000010000000100011 h
b10100 :
b10100 o
b10000 (
b10000 8
b10000 g
b10000 p
1!
#60000
0!
#65000
b1000 +
b1000 0
b1000 t
b1000 =
b1000 B
b1000 b
b0 &
b0 5
b0 c
b0 u
1<
1*
14
1D
0'
0;
b11 i
b101 )
b101 7
b101 q
b0 2
b0 s
b11 9
b11 X
b10001010000011 $
b10001010000011 >
b10001010000011 d
b10001010000011 h
b11000 :
b11000 o
b10100 (
b10100 8
b10100 g
b10100 p
1!
#70000
0!
#75000
b0 =
b0 B
b0 b
b0 +
b0 0
b0 t
b1000 F
b1000 H
b1000 &
b1000 5
b1000 c
b1000 u
b1000 6
b1000 J
b1000 v
b1 G
b1 I
b1 ^
1C
0D
0<
0*
04
b1000 ?
b1000 n
b1100011 i
b1000 )
b1000 7
b1000 q
b11 2
b11 s
b101 3
b101 r
b0 A
b0 V
b1100011 9
b1100011 X
b1100101000010001100011 $
b1100101000010001100011 >
b1100101000010001100011 d
b1100101000010001100011 h
b100000 :
b100000 o
b11000 (
b11000 8
b11000 g
b11000 p
1!
#80000
0!
#85000
b1001 +
b1001 0
b1001 t
b1001 F
b1001 H
0/
b1001 %
b1001 E
b1001 U
b1001 `
bx &
bx 5
bx c
bx u
b0 6
b0 J
b0 v
1D
1*
14
b0 G
b0 I
b0 ^
0C
b1001 ?
b1001 n
b10011 i
b111 )
b111 7
b111 q
b1001 2
b1001 s
b0 3
b0 r
b10011 9
b10011 X
b100100000000001110010011 $
b100100000000001110010011 >
b100100000000001110010011 d
b100100000000001110010011 h
b100100 :
b100100 o
b100000 (
b100000 8
b100000 g
b100000 p
1!
#90000
0!
#95000
b11111111111111111111111110001000 =
b1000100010001000 B
b1000100010001000 b
b100 %
b100 E
b100 U
b100 `
b11111111111111111111111110001000 +
b11111111111111111111111110001000 0
b11111111111111111111111110001000 t
b100 F
b100 H
b101 &
b101 5
b101 c
b101 u
1<
1D
1*
14
b100 ?
b100 n
b11 i
b1011 )
b1011 7
b1011 q
b100 2
b100 s
b11 9
b11 X
b10000000000010110000011 $
b10000000000010110000011 >
b10000000000010110000011 d
b10000000000010110000011 h
b101000 :
b101000 o
b100100 (
b100100 8
b100100 g
b100100 p
1!
#100000
0!
#105000
b10001000 +
b10001000 0
b10001000 t
b10001000 =
1D
1<
1*
14
b1100 )
b1100 7
b1100 q
b100 A
b100 V
b10000000100011000000011 $
b10000000100011000000011 >
b10000000100011000000011 d
b10000000100011000000011 h
b101100 :
b101100 o
b101000 (
b101000 8
b101000 g
b101000 p
1!
#110000
0!
#115000
b11111111111111111000100010001000 +
b11111111111111111000100010001000 0
b11111111111111111000100010001000 t
b11111111111111111000100010001000 =
1D
1<
1*
14
b1101 )
b1101 7
b1101 q
b1 A
b1 V
b10000000001011010000011 $
b10000000001011010000011 >
b10000000001011010000011 d
b10000000001011010000011 h
b110000 :
b110000 o
b101100 (
b101100 8
b101100 g
b101100 p
1!
#120000
0!
#125000
b1000100010001000 +
b1000100010001000 0
b1000100010001000 t
b1000100010001000 =
1D
1<
1*
14
b1110 )
b1110 7
b1110 q
b101 A
b101 V
b10000000101011100000011 $
b10000000101011100000011 >
b10000000101011100000011 d
b10000000101011100000011 h
b110100 :
b110100 o
b110000 (
b110000 8
b110000 g
b110000 p
1!
#130000
0!
#135000
b1000 %
b1000 E
b1000 U
b1000 `
b0 B
b0 b
b1000 +
b1000 0
b1000 t
b1000 F
b1000 H
b0 =
b0 1
b0 _
b0 a
1'
1;
1D
0<
0*
04
b1000 ?
b1000 n
b100011 i
b1000 )
b1000 7
b1000 q
b1 2
b1 s
b0 A
b0 V
b100011 9
b100011 X
b100000000010000100011 $
b100000000010000100011 >
b100000000010000100011 d
b100000000010000100011 h
b111000 :
b111000 o
b110100 (
b110100 8
b110100 g
b110100 p
1!
#140000
0!
#145000
b1010 +
b1010 0
b1010 t
b1010 %
b1010 E
b1010 U
b1010 `
b1010 F
b1010 H
b11 &
b11 5
b11 c
b11 u
1D
b1 1
b1 _
b1 a
1'
1;
b1010 ?
b1010 n
b1010 )
b1010 7
b1010 q
b10 2
b10 s
b1 A
b1 V
b1000000001010100100011 $
b1000000001010100100011 >
b1000000001010100100011 d
b1000000001010100100011 h
b111100 :
b111100 o
b111000 (
b111000 8
b111000 g
b111000 p
1!
#150000
0!
#155000
b110000000000000101 =
b1000 %
b1000 E
b1000 U
b1000 `
b110000000000000101 B
b110000000000000101 b
b110000000000000101 +
b110000000000000101 0
b110000000000000101 t
b1000 F
b1000 H
bx &
bx 5
bx c
bx u
1<
1*
14
1D
b10 1
b10 _
b10 a
0'
0;
b1000 ?
b1000 n
b11 i
b1111 )
b1111 7
b1111 q
b1000 2
b1000 s
b10 A
b10 V
b11 9
b11 X
b100000000010011110000011 $
b100000000010011110000011 >
b100000000010011110000011 d
b100000000010011110000011 h
b1000000 :
b1000000 o
b111100 (
b111100 8
b111100 g
b111100 p
1!
#160000
0!
#165000
x/
bx %
bx E
bx U
bx `
b0 B
b0 b
bx +
bx 0
bx t
bx F
bx H
bx 6
bx J
bx v
b0 =
0D
0<
0*
04
b0 ?
b0 n
bx i
bx )
bx 7
bx q
bx 2
bx s
bx 3
bx r
bx @
bx W
bx A
bx V
bx 9
bx X
bx $
bx >
bx d
bx h
b1000100 :
b1000100 o
b1000000 (
b1000000 8
b1000000 g
b1000000 p
1!
#170000
0!
#175000
b1001000 :
b1001000 o
b1000100 (
b1000100 8
b1000100 g
b1000100 p
1!
#180000
0!
#185000
b1001100 :
b1001100 o
b1001000 (
b1001000 8
b1001000 g
b1001000 p
1!
#190000
0!
#195000
b1010000 :
b1010000 o
b1001100 (
b1001100 8
b1001100 g
b1001100 p
1!
#200000
0!
#205000
b1010100 :
b1010100 o
b1010000 (
b1010000 8
b1010000 g
b1010000 p
1!
#210000
0!
#215000
b1011000 :
b1011000 o
b1010100 (
b1010100 8
b1010100 g
b1010100 p
1!
#220000
0!
#225000
b1011100 :
b1011100 o
b1011000 (
b1011000 8
b1011000 g
b1011000 p
1!
#230000
0!
#235000
b1100000 :
b1100000 o
b1011100 (
b1011100 8
b1011100 g
b1011100 p
1!
#240000
0!
#245000
b1100100 :
b1100100 o
b1100000 (
b1100000 8
b1100000 g
b1100000 p
1!
#250000
0!
#255000
b1101000 :
b1101000 o
b1100100 (
b1100100 8
b1100100 g
b1100100 p
1!
#260000
0!
#265000
b1101100 :
b1101100 o
b1101000 (
b1101000 8
b1101000 g
b1101000 p
1!
#270000
0!
#275000
b1110000 :
b1110000 o
b1101100 (
b1101100 8
b1101100 g
b1101100 p
1!
