data_mem.v
module data_mem(
    input clk,
    input logic mem_read,
    input logic mem_write,
    input logic [31:0] addr,
    input logic [31:0] data_in,

    output logic [31:0] data_out
);

    logic [31:0] mem [255:0];

    // always_comb begin
    //     if(mem_read)
    //         data_out = mem[addr[9:2]];
    //     else
    //         data_out = 32'd0;
    // end

    assign data_out = (mem_read) ? mem[addr[9:2]] : 32'd0;

    // RAM doesn't need to be reset
    // here both data and instruction memory is byte indexed
    // byte index means every byte have address

    always_ff @(posedge clk) begin

        if (mem_write) begin
            mem[addr[9:2]] <= data_in;
        end
        
    end

    
endmodule

rtl/alu.v
module alu(
    input logic [31:0] a,
    input logic [31:0] b,
    input logic [3:0] alu_ctrl,
    output logic [31:0] result,
    output logic zero 
);


localparam ADD = 4'b0000;
localparam SUB = 4'b0001;
localparam AND = 4'b0010;
localparam OR  = 4'b0011;

// use blocking assignment instead of non-blocking assignment to prevent getting prevent getting older values since all rhs side will be evaluated and then lhs will be evaluated at last
// for example
// a <= c + b;
// d <= a + e; here old value of e be used which is wrong in case of combinational circuit.

    always_comb begin
        case (alu_ctrl)
            ADD: result = a + b;
            SUB: result = a - b;
            AND: result = a & b;
            OR: result = a | b; 
            default: result = 0;
        endcase
    end

    assign zero = (result == 0);
    
endmodule

register_file.v
module register_file(
    input logic clk,
    input logic we,
    input logic [4:0] rs1,
    input logic [4:0] rs2,
    input logic [4:0] rd,
    input logic [31:0] wd,
    output logic [31:0] rd1,
    output logic [31:0] rd2
);

    logic [31:0] regfile [31:0];

    //for immidiate access of register file we used combinational/dataflow modelling.
    assign rd1 = regfile[rs1];
    assign rd2 = regfile[rs2];

    // since in write value is changing and output depends on state and input hence sequential unlike read.
    always_ff @(posedge clk) begin
        if(we && rd != 0)
            regfile[rd] <= wd;
    end

endmodule

rtl/control_unit.v
module control_unit(
    input wire [6:0] opcode,
    input wire [2:0] func3,
    input wire [6:0] func7,

    output reg reg_write,
    output reg mem_read,
    output reg mem_write,
    output reg alu_src,
    output reg branch,
    output reg [3:0] alu_ctrl
);
    localparam R_TYPE = 7'b0110011;    // Register-Register
    localparam I_TYPE = 7'b0010011;    // Immediate
    localparam LOAD   = 7'b0000011;    // Load
    localparam STORE  = 7'b0100011;    // Store
    localparam BRANCH = 7'b1100011;    // Branch

    always @(*) begin
        // Default: prevent latches
        reg_write = 0;
        mem_read = 0;
        mem_write = 0;
        alu_src = 0;
        branch = 0;
        alu_ctrl = 4'b0000;

        case (opcode)
            R_TYPE: begin
                reg_write = 1;
                case({func7, func3})
                    {7'b0000000, 3'b000}: alu_ctrl = 4'b0000;  // ADD
                    {7'b0100000, 3'b000}: alu_ctrl = 4'b0001;  // SUB
                    {7'b0000000, 3'b111}: alu_ctrl = 4'b0010;  // AND
                    {7'b0000000, 3'b110}: alu_ctrl = 4'b0011;  // OR
                    {7'b0000000, 3'b001}: alu_ctrl = 4'b0101;  // SLL
                    {7'b0000000, 3'b010}: alu_ctrl = 4'b1000;  // SLT
                    {7'b0000000, 3'b011}: alu_ctrl = 4'b1001;  // SLTU
                    {7'b0000000, 3'b100}: alu_ctrl = 4'b0100;  // XOR
                    {7'b0000000, 3'b101}: alu_ctrl = 4'b0110;  // SRL
                    {7'b0100000, 3'b101}: alu_ctrl = 4'b0111;  // SRA
                    default: alu_ctrl = 4'b1111;
                endcase
            end
            I_TYPE: begin
                reg_write = 1;
                alu_src = 1;
                case (func3)
                    3'b000: alu_ctrl = 4'b0000;  // ADDI
                    3'b010: alu_ctrl = 4'b1000;  // SLTI
                    3'b011: alu_ctrl = 4'b1001;  // SLTU
                    3'b100: alu_ctrl = 4'b0100;  // XORI
                    3'b110: alu_ctrl = 4'b0011;  // ORI
                    3'b111: alu_ctrl = 4'b0010;  // ANDI
                endcase
            end
            LOAD: begin
                case (func3)
                    3'b010: begin // LW
                        reg_write = 1;
                        mem_read = 1;
                        alu_src = 1;
                        alu_ctrl = 4'b0000;
                    end
                endcase
            end
            STORE: begin
                case (func3)
                    3'b010: begin // SW
                        mem_write = 1;
                        alu_src = 1;
                        alu_ctrl = 4'b0000;
                    end
                endcase
            end
            BRANCH: begin
                case (func3)
                    3'b000: begin // BEQ
                        branch = 1;
                        alu_ctrl = 4'b0001;
                    end
                endcase
            end
        endcase
    end

endmodule

rtl/mem.v
module inst_mem(
    input logic [31:0] addr,
    output logic [31:0] instruction
);

    logic [31:0] mem [255:0];

    // for loading instruction in memory.
    initial begin
        $readmemh("program.mem",mem);
    end

    // [1:0] is offset bit because one instruction contains 4 bytes of data so we will access as
    // 00 0000 0000 -> x0
    // 00 0000 0100 -> x4
    // 00 0000 1000 -> x8
    // 00 0000 1100 -> xC
    // ..
    // last 2 lsb bit is should be 00 and use of accessing byte of instruction
    // why till 9 because we going for 255 length of tower

    assign instruction = mem[addr[9:2]];
    
endmodule

rtl/pc_rtl.v
module pc (
    input logic clk,
    input logic rst,
    input logic [31:0] next_pc,
    output logic [31:0] pc
);
    always @(posedge clk or posedge rst) begin
        if(rst)
            pc <= 0;
        else
            pc <= next_pc;
    end

endmodule

riscv_core.v
module riscv_core(
    input logic clk,
    input logic reset
);

    //----------------------PC-----------------------
    logic [31:0] pc, next_pc;

    pc pc_inst (
        .clk(clk),
        .rst(reset),
        .next_pc(next_pc),
        .pc(pc)
    );

    //-------------------Instruction Memory----------
    logic [31:0] instr;
    inst_mem imem(
        .addr(pc),
        .instruction(instr)
    );

    //-----------------DECODE-----------------------
    logic [6:0] opcode;
    logic [2:0] func3;
    logic [6:0] func7;

    assign opcode = instr[6:0];
    assign func3 = instr[14:12];
    assign func7 = instr[31:25];

    //----------------Control Unit-----------------
    logic reg_write, mem_read, mem_write, alu_src, branch;
    logic [3:0] alu_ctrl;

    control_unit cu (
    .opcode(opcode),
    .func3(func3),
    .func7(func7),
    .reg_write(reg_write),
    .mem_read(mem_read),
    .mem_write(mem_write),
    .alu_src(alu_src),
    .branch(branch),
    .alu_ctrl(alu_ctrl)
);

// -------------------- Register File --------------------
logic [4:0] rs1, rs2, rd;
logic [31:0] rd1, rd2, write_data;

assign rs1 = instr[19:15];
assign rs2 = instr[24:20];
assign rd  = instr[11:7];

register_file rf (
    .clk(clk),
    .we(reg_write),
    .rs1(rs1),
    .rs2(rs2),
    .rd(rd),
    .wd(write_data),
    .rd1(rd1),
    .rd2(rd2)
);

// -------------------- Immediate Generator (basic) --------------------
logic [31:0] imm;

// only I-type for now 20{instr[31]} because it is for sign bit.
always_comb begin
    case(opcode)
        7'b0010011, // ADDI
        7'b0000011: // LW
            imm = {{20{instr[31]}}, instr[31:20]};

        7'b0100011: // SW (S-type)
            imm = {{20{instr[31]}}, instr[31:25], instr[11:7]};

        7'b1100011: // BEQ (B-type)
            imm = {{19{instr[31]}}, instr[31], instr[7], instr[30:25], instr[11:8], 1'b0};

        default:
            imm = 32'd0;
    endcase
end

// -------------------- ALU --------------------
logic [31:0] alu_in2, alu_result;
logic zero;

assign alu_in2 = (alu_src) ? imm : rd2;

alu alu_inst (
    .a(rd1),
    .b(alu_in2),
    .alu_ctrl(alu_ctrl),
    .result(alu_result),
    .zero(zero)
);

// -------------------- Data Memory --------------------
logic [31:0] data_out;

data_mem dmem (
    .clk(clk),
    .mem_read(mem_read),
    .mem_write(mem_write),
    .addr(alu_result),
    .data_in(rd2),
    .data_out(data_out)
);

// -------------------- Write Back --------------------
assign write_data = (mem_read) ? data_out : alu_result;      //for LOAD write_data = data_out and for add sub and other arthmatic operation write_data = alu_result

// -------------------- PC Update --------------------
assign next_pc = (branch && zero) ? pc + imm : pc + 4;       // branch is output of cu
    
endmodule

tb/tb_riscv_core.v
`timescale 1ns/1ps

module tb_riscv_core;
    
    // Testbench signals
    reg clk;
    reg reset;
    
    // Instantiate your RISC-V core
    riscv_core dut (
        .clk(clk),
        .reset(reset)
    );
    
    // Clock generation: 10ns period (100MHz)
    initial clk = 0;
    always #5 clk = ~clk;
    
    // Test program
    initial begin
        // Setup waveform dump
        $dumpfile("riscv.vcd");
        $dumpvars(0, tb_riscv_core);
        
        // Initialize instruction memory with program
        // Program:
        //   addi x1, x0, 5    -> x1 = 5
        //   addi x2, x0, 3    -> x2 = 3
        //   add  x3, x1, x2   -> x3 = 8
        //   sub  x4, x3, x2   -> x4 = 5
        
        dut.imem.mem[0] = 32'h00500093;  // addi x1, x0, 5
        dut.imem.mem[1] = 32'h00300113;  // addi x2, x0, 3
        dut.imem.mem[2] = 32'h002081b3;  // add  x3, x1, x2
      	dut.imem.mem[3] = 32'h40218233;  // sub  x4, x3, x2
        
        // Apply reset
        reset = 1;
        repeat (2) @(posedge clk);
        reset = 0;
        
        // Run for enough cycles
        repeat (10) @(posedge clk);
        
        // Display results
        $display("\n========== Test Results ==========");
        $display("x1 = %0d (expected: 5)", dut.rf.regfile[1]);
        $display("x2 = %0d (expected: 3)", dut.rf.regfile[2]);
        $display("x3 = %0d (expected: 8)", dut.rf.regfile[3]);
        $display("x4 = %0d (expected: 5)", dut.rf.regfile[4]);
        $display("==================================\n");
        
        // Check if test passed
        if (dut.rf.regfile[1] == 5 &&
            dut.rf.regfile[2] == 3 &&
            dut.rf.regfile[3] == 8 &&
            dut.rf.regfile[4] == 5) begin
            $display("TEST PASSED!\n");
        end else begin
            $display("TEST FAILED!\n");
        end
        
        $finish;
    end
    
endmodule

sim/waveform.vcd
$date
	Thu Apr  2 22:28:33 2026
$end
$version
	Icarus Verilog
$end
$timescale
	1ps
$end
$scope module tb_riscv_core $end
$var reg 1 ! clk $end
$var reg 1 " reset $end
$scope module dut $end
$var wire 1 ! clk $end
$var wire 1 " reset $end
$var wire 1 # zero $end
$var wire 32 $ write_data [31:0] $end
$var wire 5 % rs2 [4:0] $end
$var wire 5 & rs1 [4:0] $end
$var wire 1 ' reg_write $end
$var wire 32 ( rd2 [31:0] $end
$var wire 32 ) rd1 [31:0] $end
$var wire 5 * rd [4:0] $end
$var wire 32 + pc [31:0] $end
$var wire 7 , opcode [6:0] $end
$var wire 32 - next_pc [31:0] $end
$var wire 1 . mem_write $end
$var wire 1 / mem_read $end
$var wire 32 0 instr [31:0] $end
$var wire 7 1 func7 [6:0] $end
$var wire 3 2 func3 [2:0] $end
$var wire 32 3 data_out [31:0] $end
$var wire 1 4 branch $end
$var wire 1 5 alu_src $end
$var wire 32 6 alu_result [31:0] $end
$var wire 32 7 alu_in2 [31:0] $end
$var wire 4 8 alu_ctrl [3:0] $end
$var reg 32 9 imm [31:0] $end
$scope module alu_inst $end
$var wire 32 : b [31:0] $end
$var wire 1 # zero $end
$var wire 4 ; alu_ctrl [3:0] $end
$var wire 32 < a [31:0] $end
$var parameter 4 = ADD $end
$var parameter 4 > AND $end
$var parameter 4 ? OR $end
$var parameter 4 @ SUB $end
$var reg 32 A result [31:0] $end
$upscope $end
$scope module cu $end
$var wire 3 B func3 [2:0] $end
$var wire 7 C func7 [6:0] $end
$var wire 7 D opcode [6:0] $end
$var parameter 7 E BRANCH $end
$var parameter 7 F I_TYPE $end
$var parameter 7 G LOAD $end
$var parameter 7 H R_TYPE $end
$var parameter 7 I STORE $end
$var reg 4 J alu_ctrl [3:0] $end
$var reg 1 5 alu_src $end
$var reg 1 4 branch $end
$var reg 1 / mem_read $end
$var reg 1 . mem_write $end
$var reg 1 ' reg_write $end
$upscope $end
$scope module dmem $end
$var wire 32 K addr [31:0] $end
$var wire 1 ! clk $end
$var wire 1 / mem_read $end
$var wire 1 . mem_write $end
$var wire 32 L data_out [31:0] $end
$var wire 32 M data_in [31:0] $end
$upscope $end
$scope module imem $end
$var wire 32 N instruction [31:0] $end
$var wire 32 O addr [31:0] $end
$upscope $end
$scope module pc_inst $end
$var wire 1 ! clk $end
$var wire 32 P next_pc [31:0] $end
$var wire 1 " rst $end
$var reg 32 Q pc [31:0] $end
$upscope $end
$scope module rf $end
$var wire 1 ! clk $end
$var wire 5 R rd [4:0] $end
$var wire 32 S rd1 [31:0] $end
$var wire 32 T rd2 [31:0] $end
$var wire 5 U rs1 [4:0] $end
$var wire 5 V rs2 [4:0] $end
$var wire 32 W wd [31:0] $end
$var wire 1 ' we $end
$upscope $end
$upscope $end
$upscope $end
$enddefinitions $end
$comment Show the parameter values. $end
$dumpall
b100011 I
b110011 H
b11 G
b10011 F
b1100011 E
b1 @
b11 ?
b10 >
b0 =
$end
#0
$dumpvars
bx W
b101 V
b0 U
bx T
bx S
b1 R
b0 Q
b100 P
b0 O
b10100000000000010010011 N
bx M
b0 L
bx K
b0 J
b10011 D
b0 C
b0 B
bx A
bx <
b0 ;
b101 :
b101 9
b0 8
b101 7
bx 6
15
04
b0 3
b0 2
b0 1
b10100000000000010010011 0
0/
0.
b100 -
b10011 ,
b0 +
b1 *
bx )
bx (
1'
b0 &
b101 %
bx $
x#
1"
0!
$end
#5000
1!
#10000
0!
#12000
0"
#15000
b11 7
b11 :
b10 *
b10 R
b11 %
b11 V
b11 9
b1100000000000100010011 0
b1100000000000100010011 N
b1000 -
b1000 P
b100 +
b100 O
b100 Q
1!
#20000
0!
#25000
05
1'
bx 7
bx :
b11 *
b11 R
b10 %
b10 V
b1 &
b1 U
b110011 ,
b110011 D
b0 9
b1000001000000110110011 0
b1000001000000110110011 N
b1100 -
b1100 P
b1000 +
b1000 O
b1000 Q
1!
#30000
0!
#35000
0'
bx *
bx R
bx %
bx V
bx &
bx U
bx 1
bx C
bx 2
bx B
bx ,
bx D
bx 0
bx N
b10000 -
b10000 P
b1100 +
b1100 O
b1100 Q
1!
#40000
0!
#45000
b10100 -
b10100 P
b10000 +
b10000 O
b10000 Q
1!
#50000
0!
#55000
b11000 -
b11000 P
b10100 +
b10100 O
b10100 Q
1!
#60000
0!
#65000
b11100 -
b11100 P
b11000 +
b11000 O
b11000 Q
1!
#70000
0!
#75000
b100000 -
b100000 P
b11100 +
b11100 O
b11100 Q
1!
#80000
0!
#85000
b100100 -
b100100 P
b100000 +
b100000 O
b100000 Q
1!
#90000
0!
#95000
b101000 -
b101000 P
b100100 +
b100100 O
b100100 Q
1!
#100000
0!
#105000
b101100 -
b101100 P
b101000 +
b101000 O
b101000 Q
1!
